{
	"flashcardDecks": [
		{
			"id": "550e8400-e29b-41d4-a716-446655440001",
			"userId": "user-1",
			"name": "Math Formulas",
			"description": "Essential mathematics formulas for Grade 12 NSC including algebra, trigonometry, calculus, and geometry",
			"subjectId": 1,
			"cardCount": 26,
			"isPublic": true,
			"createdAt": "2026-01-01T10:00:00Z",
			"updatedAt": "2026-01-15T14:30:00Z"
		},
		{
			"id": "550e8400-e29b-41d4-a716-446655440002",
			"userId": "user-2",
			"name": "Physics Definitions",
			"description": "Key physics concepts and formulas for Grade 12 physical sciences including mechanics, waves, and electricity",
			"subjectId": 2,
			"cardCount": 28,
			"isPublic": true,
			"createdAt": "2026-01-02T09:00:00Z",
			"updatedAt": "2026-01-18T11:00:00Z"
		},
		{
			"id": "550e8400-e29b-41d4-a716-446655440003",
			"userId": "user-1",
			"name": "Chemistry Reactions",
			"description": "Important chemical reactions, periodic trends, and organic chemistry for NSC Grade 12",
			"subjectId": 2,
			"cardCount": 27,
			"isPublic": true,
			"createdAt": "2026-01-03T08:30:00Z",
			"updatedAt": "2026-01-20T16:00:00Z"
		},
		{
			"id": "550e8400-e29b-41d4-a716-446655440004",
			"userId": "user-3",
			"name": "Life Sciences",
			"description": "Cell biology, genetics, evolution, and human physiology for Grade 12 life sciences",
			"subjectId": 3,
			"cardCount": 30,
			"isPublic": true,
			"createdAt": "2026-01-04T12:00:00Z",
			"updatedAt": "2026-01-22T09:30:00Z"
		},
		{
			"id": "550e8400-e29b-41d4-a716-446655440005",
			"userId": "user-4",
			"name": "English Literature",
			"description": "Literary devices, essay writing terms, and comprehension strategies for English home language",
			"subjectId": 6,
			"cardCount": 25,
			"isPublic": true,
			"createdAt": "2026-01-05T14:00:00Z",
			"updatedAt": "2026-01-25T10:00:00Z"
		},
		{
			"id": "550e8400-e29b-41d4-a716-446655440006",
			"userId": "user-5",
			"name": "History Key Events",
			"description": "Important historical events, figures, and movements for South African and world history",
			"subjectId": 5,
			"cardCount": 28,
			"isPublic": true,
			"createdAt": "2026-01-06T11:00:00Z",
			"updatedAt": "2026-01-28T15:00:00Z"
		}
	],
	"flashcards": [
		{
			"id": "550e8400-e29b-41d4-a716-446655440011",
			"deckId": "550e8400-e29b-41d4-a716-446655440001",
			"front": "Quadratic Formula",
			"back": "x = (-b ± √(b²-4ac)) / 2a",
			"imageUrl": null,
			"difficulty": "medium",
			"timesReviewed": 5,
			"timesCorrect": 4,
			"easeFactor": "2.5",
			"intervalDays": 4,
			"repetitions": 3,
			"nextReview": "2026-03-15T10:00:00Z",
			"lastReview": "2026-03-11T10:00:00Z",
			"createdAt": "2026-01-01T10:00:00Z",
			"updatedAt": "2026-03-11T10:00:00Z"
		},
		{
			"id": "550e8400-e29b-41d4-a716-446655440012",
			"deckId": "550e8400-e29b-41d4-a716-446655440001",
			"front": "Derivative of x^n",
			"back": "d/dx(x^n) = nx^(n-1)",
			"imageUrl": null,
			"difficulty": "easy",
			"timesReviewed": 7,
			"timesCorrect": 6,
			"easeFactor": "2.6",
			"intervalDays": 8,
			"repetitions": 5,
			"nextReview": "2026-03-18T10:00:00Z",
			"lastReview": "2026-03-10T10:00:00Z",
			"createdAt": "2026-01-01T10:00:00Z",
			"updatedAt": "2026-03-10T10:00:00Z"
		},
		{
			"id": "550e8400-e29b-41d4-a716-446655440013",
			"deckId": "550e8400-e29b-41d4-a716-446655440001",
			"front": "Integral of x^n",
			"back": "∫x^n dx = x^(n+1)/(n+1) + C (for n ≠ -1)",
			"imageUrl": null,
			"difficulty": "medium",
			"timesReviewed": 4,
			"timesCorrect": 3,
			"easeFactor": "2.3",
			"intervalDays": 3,
			"repetitions": 2,
			"nextReview": "2026-03-14T10:00:00Z",
			"lastReview": "2026-03-11T10:00:00Z",
			"createdAt": "2026-01-01T10:00:00Z",
			"updatedAt": "2026-03-11T10:00:00Z"
		},
		{
			"id": "550e8400-e29b-41d4-a716-446655440014",
			"deckId": "550e8400-e29b-41d4-a716-446655440001",
			"front": "Sine Rule",
			"back": "a/sin A = b/sin B = c/sin C",
			"imageUrl": null,
			"difficulty": "medium",
			"timesReviewed": 6,
			"timesCorrect": 5,
			"easeFactor": "2.5",
			"intervalDays": 5,
			"repetitions": 4,
			"nextReview": "2026-03-16T10:00:00Z",
			"lastReview": "2026-03-11T10:00:00Z",
			"createdAt": "2026-01-02T10:00:00Z",
			"updatedAt": "2026-03-11T10:00:00Z"
		},
		{
			"id": "550e8400-e29b-41d4-a716-446655440015",
			"deckId": "550e8400-e29b-41d4-a716-446655440001",
			"front": "Cosine Rule",
			"back": "c² = a² + b² - 2ab cos C",
			"imageUrl": null,
			"difficulty": "medium",
			"timesReviewed": 5,
			"timesCorrect": 4,
			"easeFactor": "2.4",
			"intervalDays": 4,
			"repetitions": 3,
			"nextReview": "2026-03-15T10:00:00Z",
			"lastReview": "2026-03-11T10:00:00Z",
			"createdAt": "2026-01-02T10:00:00Z",
			"updatedAt": "2026-03-11T10:00:00Z"
		},
		{
			"id": "550e8400-e29b-41d4-a716-446655440016",
			"deckId": "550e8400-e29b-41d4-a716-446655440001",
			"front": "Area of a Triangle",
			"back": "Area = ½ ab sin C",
			"imageUrl": null,
			"difficulty": "easy",
			"timesReviewed": 8,
			"timesCorrect": 7,
			"easeFactor": "2.7",
			"intervalDays": 10,
			"repetitions": 6,
			"nextReview": "2026-03-20T10:00:00Z",
			"lastReview": "2026-03-10T10:00:00Z",
			"createdAt": "2026-01-02T10:00:00Z",
			"updatedAt": "2026-03-10T10:00:00Z"
		},
		{
			"id": "550e8400-e29b-41d4-a716-446655440017",
			"deckId": "550e8400-e29b-41d4-a716-446655440001",
			"front": "Pythagorean Identity",
			"back": "sin²θ + cos²θ = 1",
			"imageUrl": null,
			"difficulty": "easy",
			"timesReviewed": 9,
			"timesCorrect": 8,
			"easeFactor": "2.8",
			"intervalDays": 14,
			"repetitions": 7,
			"nextReview": "2026-03-24T10:00:00Z",
			"lastReview": "2026-03-10T10:00:00Z",
			"createdAt": "2026-01-03T10:00:00Z",
			"updatedAt": "2026-03-10T10:00:00Z"
		},
		{
			"id": "550e8400-e29b-41d4-a716-446655440018",
			"deckId": "550e8400-e29b-41d4-a716-446655440001",
			"front": "Double Angle: sin 2θ",
			"back": "sin 2θ = 2 sin θ cos θ",
			"imageUrl": null,
			"difficulty": "medium",
			"timesReviewed": 5,
			"timesCorrect": 4,
			"easeFactor": "2.4",
			"intervalDays": 5,
			"repetitions": 3,
			"nextReview": "2026-03-16T10:00:00Z",
			"lastReview": "2026-03-11T10:00:00Z",
			"createdAt": "2026-01-03T10:00:00Z",
			"updatedAt": "2026-03-11T10:00:00Z"
		},
		{
			"id": "550e8400-e29b-41d4-a716-446655440019",
			"deckId": "550e8400-e29b-41d4-a716-446655440001",
			"front": "Double Angle: cos 2θ",
			"back": "cos 2θ = cos²θ - sin²θ = 2cos²θ - 1 = 1 - 2sin²θ",
			"imageUrl": null,
			"difficulty": "medium",
			"timesReviewed": 4,
			"timesCorrect": 3,
			"easeFactor": "2.3",
			"intervalDays": 4,
			"repetitions": 2,
			"nextReview": "2026-03-15T10:00:00Z",
			"lastReview": "2026-03-11T10:00:00Z",
			"createdAt": "2026-01-03T10:00:00Z",
			"updatedAt": "2026-03-11T10:00:00Z"
		},
		{
			"id": "550e8400-e29b-41d4-a716-446655440020",
			"deckId": "550e8400-e29b-41d4-a716-446655440001",
			"front": "Sum of Arithmetic Sequence",
			"back": "S_n = n/2(2a + (n-1)d)",
			"imageUrl": null,
			"difficulty": "easy",
			"timesReviewed": 7,
			"timesCorrect": 6,
			"easeFactor": "2.6",
			"intervalDays": 8,
			"repetitions": 5,
			"nextReview": "2026-03-18T10:00:00Z",
			"lastReview": "2026-03-10T10:00:00Z",
			"createdAt": "2026-01-04T10:00:00Z",
			"updatedAt": "2026-03-10T10:00:00Z"
		},
		{
			"id": "550e8400-e29b-41d4-a716-446655440021",
			"deckId": "550e8400-e29b-41d4-a716-446655440001",
			"front": "Sum of Geometric Sequence",
			"back": "S_n = a(r^n - 1)/(r - 1) for r ≠ 1",
			"imageUrl": null,
			"difficulty": "medium",
			"timesReviewed": 5,
			"timesCorrect": 4,
			"easeFactor": "2.5",
			"intervalDays": 6,
			"repetitions": 3,
			"nextReview": "2026-03-16T10:00:00Z",
			"lastReview": "2026-03-10T10:00:00Z",
			"createdAt": "2026-01-04T10:00:00Z",
			"updatedAt": "2026-03-10T10:00:00Z"
		},
		{
			"id": "550e8400-e29b-41d4-a716-446655440022",
			"deckId": "550e8400-e29b-41d4-a716-446655440001",
			"front": "Compound Interest Formula",
			"back": "A = P(1 + i)^n",
			"imageUrl": null,
			"difficulty": "easy",
			"timesReviewed": 6,
			"timesCorrect": 5,
			"easeFactor": "2.5",
			"intervalDays": 7,
			"repetitions": 4,
			"nextReview": "2026-03-17T10:00:00Z",
			"lastReview": "2026-03-10T10:00:00Z",
			"createdAt": "2026-01-04T10:00:00Z",
			"updatedAt": "2026-03-10T10:00:00Z"
		},
		{
			"id": "550e8400-e29b-41d4-a716-446655440023",
			"deckId": "550e8400-e29b-41d4-a716-446655440001",
			"front": "Equation of a Circle",
			"back": "(x - a)² + (y - b)² = r²",
			"imageUrl": null,
			"difficulty": "easy",
			"timesReviewed": 8,
			"timesCorrect": 7,
			"easeFactor": "2.7",
			"intervalDays": 10,
			"repetitions": 6,
			"nextReview": "2026-03-20T10:00:00Z",
			"lastReview": "2026-03-10T10:00:00Z",
			"createdAt": "2026-01-05T10:00:00Z",
			"updatedAt": "2026-03-10T10:00:00Z"
		},
		{
			"id": "550e8400-e29b-41d4-a716-446655440024",
			"deckId": "550e8400-e29b-41d4-a716-446655440001",
			"front": "Gradient-Intercept Form",
			"back": "y = mx + c where m is gradient and c is y-intercept",
			"imageUrl": null,
			"difficulty": "easy",
			"timesReviewed": 10,
			"timesCorrect": 9,
			"easeFactor": "2.9",
			"intervalDays": 15,
			"repetitions": 8,
			"nextReview": "2026-03-25T10:00:00Z",
			"lastReview": "2026-03-10T10:00:00Z",
			"createdAt": "2026-01-05T10:00:00Z",
			"updatedAt": "2026-03-10T10:00:00Z"
		},
		{
			"id": "550e8400-e29b-41d4-a716-446655440025",
			"deckId": "550e8400-e29b-41d4-a716-446655440001",
			"front": "Chain Rule",
			"back": "d/dx[f(g(x))] = f'(g(x)) · g'(x)",
			"imageUrl": null,
			"difficulty": "hard",
			"timesReviewed": 3,
			"timesCorrect": 2,
			"easeFactor": "2.0",
			"intervalDays": 2,
			"repetitions": 1,
			"nextReview": "2026-03-13T10:00:00Z",
			"lastReview": "2026-03-11T10:00:00Z",
			"createdAt": "2026-01-05T10:00:00Z",
			"updatedAt": "2026-03-11T10:00:00Z"
		},
		{
			"id": "550e8400-e29b-41d4-a716-446655440026",
			"deckId": "550e8400-e29b-41d4-a716-446655440001",
			"front": "Product Rule",
			"back": "d/dx(uv) = u'v + uv'",
			"imageUrl": null,
			"difficulty": "medium",
			"timesReviewed": 5,
			"timesCorrect": 4,
			"easeFactor": "2.4",
			"intervalDays": 5,
			"repetitions": 3,
			"nextReview": "2026-03-16T10:00:00Z",
			"lastReview": "2026-03-11T10:00:00Z",
			"createdAt": "2026-01-05T10:00:00Z",
			"updatedAt": "2026-03-11T10:00:00Z"
		},
		{
			"id": "550e8400-e29b-41d4-a716-446655440027",
			"deckId": "550e8400-e29b-41d4-a716-446655440001",
			"front": "Quotient Rule",
			"back": "d/dx(u/v) = (u'v - uv')/v²",
			"imageUrl": null,
			"difficulty": "hard",
			"timesReviewed": 4,
			"timesCorrect": 2,
			"easeFactor": "1.9",
			"intervalDays": 2,
			"repetitions": 1,
			"nextReview": "2026-03-13T10:00:00Z",
			"lastReview": "2026-03-11T10:00:00Z",
			"createdAt": "2026-01-06T10:00:00Z",
			"updatedAt": "2026-03-11T10:00:00Z"
		},
		{
			"id": "550e8400-e29b-41d4-a716-446655440028",
			"deckId": "550e8400-e29b-41d4-a716-446655440001",
			"front": "Logarithm: Change of Base",
			"back": "log_a(x) = log(x)/log(a) = ln(x)/ln(a)",
			"imageUrl": null,
			"difficulty": "medium",
			"timesReviewed": 6,
			"timesCorrect": 5,
			"easeFactor": "2.5",
			"intervalDays": 6,
			"repetitions": 4,
			"nextReview": "2026-03-17T10:00:00Z",
			"lastReview": "2026-03-11T10:00:00Z",
			"createdAt": "2026-01-06T10:00:00Z",
			"updatedAt": "2026-03-11T10:00:00Z"
		},
		{
			"id": "550e8400-e29b-41d4-a716-446655440029",
			"deckId": "550e8400-e29b-41d4-a716-446655440001",
			"front": "Exponential: e^x derivative",
			"back": "d/dx(e^x) = e^x",
			"imageUrl": null,
			"difficulty": "easy",
			"timesReviewed": 9,
			"timesCorrect": 8,
			"easeFactor": "2.8",
			"intervalDays": 12,
			"repetitions": 7,
			"nextReview": "2026-03-22T10:00:00Z",
			"lastReview": "2026-03-10T10:00:00Z",
			"createdAt": "2026-01-06T10:00:00Z",
			"updatedAt": "2026-03-10T10:00:00Z"
		},
		{
			"id": "550e8400-e29b-41d4-a716-446655440030",
			"deckId": "550e8400-e29b-41d4-a716-446655440001",
			"front": "Natural Log: ln x derivative",
			"back": "d/dx(ln x) = 1/x",
			"imageUrl": null,
			"difficulty": "easy",
			"timesReviewed": 8,
			"timesCorrect": 7,
			"easeFactor": "2.7",
			"intervalDays": 10,
			"repetitions": 6,
			"nextReview": "2026-03-20T10:00:00Z",
			"lastReview": "2026-03-10T10:00:00Z",
			"createdAt": "2026-01-07T10:00:00Z",
			"updatedAt": "2026-03-10T10:00:00Z"
		},
		{
			"id": "550e8400-e29b-41d4-a716-446655440031",
			"deckId": "550e8400-e29b-41d4-a716-446655440001",
			"front": "Definite Integral",
			"back": "∫_a^b f(x)dx = F(b) - F(a)",
			"imageUrl": null,
			"difficulty": "medium",
			"timesReviewed": 5,
			"timesCorrect": 4,
			"easeFactor": "2.4",
			"intervalDays": 5,
			"repetitions": 3,
			"nextReview": "2026-03-16T10:00:00Z",
			"lastReview": "2026-03-11T10:00:00Z",
			"createdAt": "2026-01-07T10:00:00Z",
			"updatedAt": "2026-03-11T10:00:00Z"
		},
		{
			"id": "550e8400-e29b-41d4-a716-446655440032",
			"deckId": "550e8400-e29b-41d4-a716-446655440001",
			"front": "Factor Formula: cos²θ",
			"back": "cos²θ = (1 + cos 2θ)/2",
			"imageUrl": null,
			"difficulty": "medium",
			"timesReviewed": 4,
			"timesCorrect": 3,
			"easeFactor": "2.3",
			"intervalDays": 4,
			"repetitions": 2,
			"nextReview": "2026-03-15T10:00:00Z",
			"lastReview": "2026-03-11T10:00:00Z",
			"createdAt": "2026-01-08T10:00:00Z",
			"updatedAt": "2026-03-11T10:00:00Z"
		},
		{
			"id": "550e8400-e29b-41d4-a716-446655440033",
			"deckId": "550e8400-e29b-41d4-a716-446655440001",
			"front": "Factor Formula: sin²θ",
			"back": "sin²θ = (1 - cos 2θ)/2",
			"imageUrl": null,
			"difficulty": "medium",
			"timesReviewed": 4,
			"timesCorrect": 3,
			"easeFactor": "2.3",
			"intervalDays": 4,
			"repetitions": 2,
			"nextReview": "2026-03-15T10:00:00Z",
			"lastReview": "2026-03-11T10:00:00Z",
			"createdAt": "2026-01-08T10:00:00Z",
			"updatedAt": "2026-03-11T10:00:00Z"
		},
		{
			"id": "550e8400-e29b-41d4-a716-446655440034",
			"deckId": "550e8400-e29b-41d4-a716-446655440001",
			"front": "2sin A cos B formula",
			"back": "2 sin A cos B = sin(A + B) + sin(A - B)",
			"imageUrl": null,
			"difficulty": "hard",
			"timesReviewed": 3,
			"timesCorrect": 2,
			"easeFactor": "2.0",
			"intervalDays": 2,
			"repetitions": 1,
			"nextReview": "2026-03-13T10:00:00Z",
			"lastReview": "2026-03-11T10:00:00Z",
			"createdAt": "2026-01-08T10:00:00Z",
			"updatedAt": "2026-03-11T10:00:00Z"
		},
		{
			"id": "550e8400-e29b-41d4-a716-446655440035",
			"deckId": "550e8400-e29b-41d4-a716-446655440001",
			"front": "2cos A cos B formula",
			"back": "2 cos A cos B = cos(A + B) + cos(A - B)",
			"imageUrl": null,
			"difficulty": "hard",
			"timesReviewed": 3,
			"timesCorrect": 2,
			"easeFactor": "2.0",
			"intervalDays": 2,
			"repetitions": 1,
			"nextReview": "2026-03-13T10:00:00Z",
			"lastReview": "2026-03-11T10:00:00Z",
			"createdAt": "2026-01-08T10:00:00Z",
			"updatedAt": "2026-03-11T10:00:00Z"
		},
		{
			"id": "550e8400-e29b-41d4-a716-446655440036",
			"deckId": "550e8400-e29b-41d4-a716-446655440001",
			"front": "Completing the Square",
			"back": "x² + bx + c = (x + b/2)² - (b/2)² + c",
			"imageUrl": null,
			"difficulty": "medium",
			"timesReviewed": 6,
			"timesCorrect": 5,
			"easeFactor": "2.5",
			"intervalDays": 6,
			"repetitions": 4,
			"nextReview": "2026-03-17T10:00:00Z",
			"lastReview": "2026-03-11T10:00:00Z",
			"createdAt": "2026-01-09T10:00:00Z",
			"updatedAt": "2026-03-11T10:00:00Z"
		},
		{
			"id": "550e8400-e29b-41d4-a716-446655440037",
			"deckId": "550e8400-e29b-41d4-a716-446655440002",
			"front": "Newton's First Law",
			"back": "An object remains at rest or in uniform motion unless acted upon by an external force",
			"imageUrl": null,
			"difficulty": "easy",
			"timesReviewed": 7,
			"timesCorrect": 6,
			"easeFactor": "2.6",
			"intervalDays": 8,
			"repetitions": 5,
			"nextReview": "2026-03-18T10:00:00Z",
			"lastReview": "2026-03-10T10:00:00Z",
			"createdAt": "2026-01-02T09:00:00Z",
			"updatedAt": "2026-03-10T10:00:00Z"
		},
		{
			"id": "550e8400-e29b-41d4-a716-446655440038",
			"deckId": "550e8400-e29b-41d4-a716-446655440002",
			"front": "Newton's Second Law",
			"back": "F = ma (Force equals mass times acceleration)",
			"imageUrl": null,
			"difficulty": "easy",
			"timesReviewed": 9,
			"timesCorrect": 8,
			"easeFactor": "2.8",
			"intervalDays": 12,
			"repetitions": 7,
			"nextReview": "2026-03-22T10:00:00Z",
			"lastReview": "2026-03-10T10:00:00Z",
			"createdAt": "2026-01-02T09:00:00Z",
			"updatedAt": "2026-03-10T10:00:00Z"
		},
		{
			"id": "550e8400-e29b-41d4-a716-446655440039",
			"deckId": "550e8400-e29b-41d4-a716-446655440002",
			"front": "Newton's Third Law",
			"back": "For every action, there is an equal and opposite reaction",
			"imageUrl": null,
			"difficulty": "easy",
			"timesReviewed": 8,
			"timesCorrect": 7,
			"easeFactor": "2.7",
			"intervalDays": 10,
			"repetitions": 6,
			"nextReview": "2026-03-20T10:00:00Z",
			"lastReview": "2026-03-10T10:00:00Z",
			"createdAt": "2026-01-02T09:00:00Z",
			"updatedAt": "2026-03-10T10:00:00Z"
		},
		{
			"id": "550e8400-e29b-41d4-a716-446655440040",
			"deckId": "550e8400-e29b-41d4-a716-446655440002",
			"front": "Kinematic Equation 1",
			"back": "v = u + at (final velocity = initial velocity + acceleration × time)",
			"imageUrl": null,
			"difficulty": "easy",
			"timesReviewed": 10,
			"timesCorrect": 9,
			"easeFactor": "2.9",
			"intervalDays": 15,
			"repetitions": 8,
			"nextReview": "2026-03-25T10:00:00Z",
			"lastReview": "2026-03-10T10:00:00Z",
			"createdAt": "2026-01-03T09:00:00Z",
			"updatedAt": "2026-03-10T10:00:00Z"
		},
		{
			"id": "550e8400-e29b-41d4-a716-446655440041",
			"deckId": "550e8400-e29b-41d4-a716-446655440002",
			"front": "Kinematic Equation 2",
			"back": "s = ut + ½at² (displacement = initial velocity × time + ½ × acceleration × time²)",
			"imageUrl": null,
			"difficulty": "medium",
			"timesReviewed": 6,
			"timesCorrect": 5,
			"easeFactor": "2.5",
			"intervalDays": 6,
			"repetitions": 4,
			"nextReview": "2026-03-17T10:00:00Z",
			"lastReview": "2026-03-11T10:00:00Z",
			"createdAt": "2026-01-03T09:00:00Z",
			"updatedAt": "2026-03-11T10:00:00Z"
		},
		{
			"id": "550e8400-e29b-41d4-a716-446655440042",
			"deckId": "550e8400-e29b-41d4-a716-446655440002",
			"front": "Kinematic Equation 3",
			"back": "v² = u² + 2as (final velocity squared = initial velocity squared + 2 × acceleration × displacement)",
			"imageUrl": null,
			"difficulty": "medium",
			"timesReviewed": 5,
			"timesCorrect": 4,
			"easeFactor": "2.4",
			"intervalDays": 5,
			"repetitions": 3,
			"nextReview": "2026-03-16T10:00:00Z",
			"lastReview": "2026-03-11T10:00:00Z",
			"createdAt": "2026-01-03T09:00:00Z",
			"updatedAt": "2026-03-11T10:00:00Z"
		},
		{
			"id": "550e8400-e29b-41d4-a716-446655440043",
			"deckId": "550e8400-e29b-41d4-a716-446655440002",
			"front": "Kinetic Energy",
			"back": "KE = ½mv² (Kinetic energy = ½ × mass × velocity squared)",
			"imageUrl": null,
			"difficulty": "easy",
			"timesReviewed": 8,
			"timesCorrect": 7,
			"easeFactor": "2.7",
			"intervalDays": 10,
			"repetitions": 6,
			"nextReview": "2026-03-20T10:00:00Z",
			"lastReview": "2026-03-10T10:00:00Z",
			"createdAt": "2026-01-04T09:00:00Z",
			"updatedAt": "2026-03-10T10:00:00Z"
		},
		{
			"id": "550e8400-e29b-41d4-a716-446655440044",
			"deckId": "550e8400-e29b-41d4-a716-446655440002",
			"front": "Gravitational Potential Energy",
			"back": "GPE = mgh (mass × gravitational acceleration × height)",
			"imageUrl": null,
			"difficulty": "easy",
			"timesReviewed": 9,
			"timesCorrect": 8,
			"easeFactor": "2.8",
			"intervalDays": 12,
			"repetitions": 7,
			"nextReview": "2026-03-22T10:00:00Z",
			"lastReview": "2026-03-10T10:00:00Z",
			"createdAt": "2026-01-04T09:00:00Z",
			"updatedAt": "2026-03-10T10:00:00Z"
		},
		{
			"id": "550e8400-e29b-41d4-a716-446655440045",
			"deckId": "550e8400-e29b-41d4-a716-446655440002",
			"front": "Work Done",
			"back": "W = Fd cos θ (Work = force × displacement × cos of angle between force and displacement)",
			"imageUrl": null,
			"difficulty": "medium",
			"timesReviewed": 5,
			"timesCorrect": 4,
			"easeFactor": "2.4",
			"intervalDays": 5,
			"repetitions": 3,
			"nextReview": "2026-03-16T10:00:00Z",
			"lastReview": "2026-03-11T10:00:00Z",
			"createdAt": "2026-01-04T09:00:00Z",
			"updatedAt": "2026-03-11T10:00:00Z"
		},
		{
			"id": "550e8400-e29b-41d4-a716-446655440046",
			"deckId": "550e8400-e29b-41d4-a716-446655440002",
			"front": "Power",
			"back": "P = W/t = Fv (Power = work done / time = force × velocity)",
			"imageUrl": null,
			"difficulty": "medium",
			"timesReviewed": 6,
			"timesCorrect": 5,
			"easeFactor": "2.5",
			"intervalDays": 6,
			"repetitions": 4,
			"nextReview": "2026-03-17T10:00:00Z",
			"lastReview": "2026-03-11T10:00:00Z",
			"createdAt": "2026-01-05T09:00:00Z",
			"updatedAt": "2026-03-11T10:00:00Z"
		},
		{
			"id": "550e8400-e29b-41d4-a716-446655440047",
			"deckId": "550e8400-e29b-41d4-a716-446655440002",
			"front": "Wave Equation",
			"back": "v = fλ (velocity = frequency × wavelength)",
			"imageUrl": null,
			"difficulty": "easy",
			"timesReviewed": 8,
			"timesCorrect": 7,
			"easeFactor": "2.7",
			"intervalDays": 10,
			"repetitions": 6,
			"nextReview": "2026-03-20T10:00:00Z",
			"lastReview": "2026-03-10T10:00:00Z",
			"createdAt": "2026-01-05T09:00:00Z",
			"updatedAt": "2026-03-10T10:00:00Z"
		},
		{
			"id": "550e8400-e29b-41d4-a716-446655440048",
			"deckId": "550e8400-e29b-41d4-a716-446655440002",
			"front": "Period-Frequency Relationship",
			"back": "T = 1/f (Period = 1 / frequency)",
			"imageUrl": null,
			"difficulty": "easy",
			"timesReviewed": 7,
			"timesCorrect": 6,
			"easeFactor": "2.6",
			"intervalDays": 8,
			"repetitions": 5,
			"nextReview": "2026-03-18T10:00:00Z",
			"lastReview": "2026-03-10T10:00:00Z",
			"createdAt": "2026-01-05T09:00:00Z",
			"updatedAt": "2026-03-10T10:00:00Z"
		},
		{
			"id": "550e8400-e29b-41d4-a716-446655440049",
			"deckId": "550e8400-e29b-41d4-a716-446655440002",
			"front": "Ohm's Law",
			"back": "V = IR (Voltage = current × resistance)",
			"imageUrl": null,
			"difficulty": "easy",
			"timesReviewed": 9,
			"timesCorrect": 8,
			"easeFactor": "2.8",
			"intervalDays": 12,
			"repetitions": 7,
			"nextReview": "2026-03-22T10:00:00Z",
			"lastReview": "2026-03-10T10:00:00Z",
			"createdAt": "2026-01-06T09:00:00Z",
			"updatedAt": "2026-03-10T10:00:00Z"
		},
		{
			"id": "550e8400-e29b-41d4-a716-446655440050",
			"deckId": "550e8400-e29b-41d4-a716-446655440002",
			"front": "Electrical Power",
			"back": "P = IV = I²R = V²/R (Power = current × voltage)",
			"imageUrl": null,
			"difficulty": "medium",
			"timesReviewed": 5,
			"timesCorrect": 4,
			"easeFactor": "2.4",
			"intervalDays": 5,
			"repetitions": 3,
			"nextReview": "2026-03-16T10:00:00Z",
			"lastReview": "2026-03-11T10:00:00Z",
			"createdAt": "2026-01-06T09:00:00Z",
			"updatedAt": "2026-03-11T10:00:00Z"
		},
		{
			"id": "550e8400-e29b-41d4-a716-446655440051",
			"deckId": "550e8400-e29b-41d4-a716-446655440002",
			"front": "Momentum",
			"back": "p = mv (momentum = mass × velocity)",
			"imageUrl": null,
			"difficulty": "easy",
			"timesReviewed": 8,
			"timesCorrect": 7,
			"easeFactor": "2.7",
			"intervalDays": 10,
			"repetitions": 6,
			"nextReview": "2026-03-20T10:00:00Z",
			"lastReview": "2026-03-10T10:00:00Z",
			"createdAt": "2026-01-06T09:00:00Z",
			"updatedAt": "2026-03-10T10:00:00Z"
		},
		{
			"id": "550e8400-e29b-41d4-a716-446655440052",
			"deckId": "550e8400-e29b-41d4-a716-446655440002",
			"front": "Conservation of Momentum",
			"back": "m₁u₁ + m₂u₂ = m₁v₁ + m₂v₂ (total momentum before = total momentum after)",
			"imageUrl": null,
			"difficulty": "medium",
			"timesReviewed": 5,
			"timesCorrect": 4,
			"easeFactor": "2.5",
			"intervalDays": 6,
			"repetitions": 3,
			"nextReview": "2026-03-17T10:00:00Z",
			"lastReview": "2026-03-11T10:00:00Z",
			"createdAt": "2026-01-07T09:00:00Z",
			"updatedAt": "2026-03-11T10:00:00Z"
		},
		{
			"id": "550e8400-e29b-41d4-a716-446655440053",
			"deckId": "550e8400-e29b-41d4-a716-446655440002",
			"front": "Impulse",
			"back": "J = FΔt = Δp (Impulse = force × time = change in momentum)",
			"imageUrl": null,
			"difficulty": "medium",
			"timesReviewed": 4,
			"timesCorrect": 3,
			"easeFactor": "2.3",
			"intervalDays": 4,
			"repetitions": 2,
			"nextReview": "2026-03-15T10:00:00Z",
			"lastReview": "2026-03-11T10:00:00Z",
			"createdAt": "2026-01-07T09:00:00Z",
			"updatedAt": "2026-03-11T10:00:00Z"
		},
		{
			"id": "550e8400-e29b-41d4-a716-446655440054",
			"deckId": "550e8400-e29b-41d4-a716-446655440002",
			"front": "Universal Gravitation",
			"back": "F = Gm₁m₂/r² (Force = gravitational constant × mass1 × mass2 / distance²)",
			"imageUrl": null,
			"difficulty": "hard",
			"timesReviewed": 3,
			"timesCorrect": 2,
			"easeFactor": "2.0",
			"intervalDays": 2,
			"repetitions": 1,
			"nextReview": "2026-03-13T10:00:00Z",
			"lastReview": "2026-03-11T10:00:00Z",
			"createdAt": "2026-01-07T09:00:00Z",
			"updatedAt": "2026-03-11T10:00:00Z"
		},
		{
			"id": "550e8400-e29b-41d4-a716-446655440055",
			"deckId": "550e8400-e29b-41d4-a716-446655440002",
			"front": "Electric Field Strength",
			"back": "E = F/q = kQ/r² (Electric field = force / charge)",
			"imageUrl": null,
			"difficulty": "hard",
			"timesReviewed": 3,
			"timesCorrect": 2,
			"easeFactor": "1.9",
			"intervalDays": 2,
			"repetitions": 1,
			"nextReview": "2026-03-13T10:00:00Z",
			"lastReview": "2026-03-11T10:00:00Z",
			"createdAt": "2026-01-08T09:00:00Z",
			"updatedAt": "2026-03-11T10:00:00Z"
		},
		{
			"id": "550e8400-e29b-41d4-a716-446655440056",
			"deckId": "550e8400-e29b-41d4-a716-446655440002",
			"front": "Hooke's Law",
			"back": "F = -kx (Force = -spring constant × extension)",
			"imageUrl": null,
			"difficulty": "easy",
			"timesReviewed": 7,
			"timesCorrect": 6,
			"easeFactor": "2.6",
			"intervalDays": 8,
			"repetitions": 5,
			"nextReview": "2026-03-18T10:00:00Z",
			"lastReview": "2026-03-10T10:00:00Z",
			"createdAt": "2026-01-08T09:00:00Z",
			"updatedAt": "2026-03-10T10:00:00Z"
		},
		{
			"id": "550e8400-e29b-41d4-a716-446655440057",
			"deckId": "550e8400-e29b-41d4-a716-446655440002",
			"front": "Pressure",
			"back": "P = F/A (Pressure = force / area)",
			"imageUrl": null,
			"difficulty": "easy",
			"timesReviewed": 8,
			"timesCorrect": 7,
			"easeFactor": "2.7",
			"intervalDays": 10,
			"repetitions": 6,
			"nextReview": "2026-03-20T10:00:00Z",
			"lastReview": "2026-03-10T10:00:00Z",
			"createdAt": "2026-01-09T09:00:00Z",
			"updatedAt": "2026-03-10T10:00:00Z"
		},
		{
			"id": "550e8400-e29b-41d4-a716-446655440058",
			"deckId": "550e8400-e29b-41d4-a716-446655440002",
			"front": "Doppler Effect",
			"back": "f' = f(v ± vo)/(v ∓ vs) (observed frequency changes with relative motion)",
			"imageUrl": null,
			"difficulty": "hard",
			"timesReviewed": 3,
			"timesCorrect": 2,
			"easeFactor": "2.0",
			"intervalDays": 2,
			"repetitions": 1,
			"nextReview": "2026-03-13T10:00:00Z",
			"lastReview": "2026-03-11T10:00:00Z",
			"createdAt": "2026-01-09T09:00:00Z",
			"updatedAt": "2026-03-11T10:00:00Z"
		},
		{
			"id": "550e8400-e29b-41d4-a716-446655440059",
			"deckId": "550e8400-e29b-41d4-a716-446655440002",
			"front": "Lens Equation",
			"back": "1/f = 1/do + 1/di (1/focal length = 1/object distance + 1/image distance)",
			"imageUrl": null,
			"difficulty": "medium",
			"timesReviewed": 5,
			"timesCorrect": 4,
			"easeFactor": "2.4",
			"intervalDays": 5,
			"repetitions": 3,
			"nextReview": "2026-03-16T10:00:00Z",
			"lastReview": "2026-03-11T10:00:00Z",
			"createdAt": "2026-01-09T09:00:00Z",
			"updatedAt": "2026-03-11T10:00:00Z"
		},
		{
			"id": "550e8400-e29b-41d4-a716-446655440060",
			"deckId": "550e8400-e29b-41d4-a716-446655440002",
			"front": "Snell's Law",
			"back": "n₁ sin θ₁ = n₂ sin θ₂ (refraction angle depends on refractive indices)",
			"imageUrl": null,
			"difficulty": "medium",
			"timesReviewed": 4,
			"timesCorrect": 3,
			"easeFactor": "2.3",
			"intervalDays": 4,
			"repetitions": 2,
			"nextReview": "2026-03-15T10:00:00Z",
			"lastReview": "2026-03-11T10:00:00Z",
			"createdAt": "2026-01-10T09:00:00Z",
			"updatedAt": "2026-03-11T10:00:00Z"
		},
		{
			"id": "550e8400-e29b-41d4-a716-446655440061",
			"deckId": "550e8400-e29b-41d4-a716-446655440002",
			"front": "Specific Heat Capacity",
			"back": "Q = mcΔT (heat = mass × specific heat capacity × temperature change)",
			"imageUrl": null,
			"difficulty": "easy",
			"timesReviewed": 7,
			"timesCorrect": 6,
			"easeFactor": "2.6",
			"intervalDays": 8,
			"repetitions": 5,
			"nextReview": "2026-03-18T10:00:00Z",
			"lastReview": "2026-03-10T10:00:00Z",
			"createdAt": "2026-01-10T09:00:00Z",
			"updatedAt": "2026-03-10T10:00:00Z"
		},
		{
			"id": "550e8400-e29b-41d4-a716-446655440062",
			"deckId": "550e8400-e29b-41d4-a716-446655440002",
			"front": "Efficiency",
			"back": "Efficiency = (useful output / input) × 100%",
			"imageUrl": null,
			"difficulty": "easy",
			"timesReviewed": 8,
			"timesCorrect": 7,
			"easeFactor": "2.7",
			"intervalDays": 10,
			"repetitions": 6,
			"nextReview": "2026-03-20T10:00:00Z",
			"lastReview": "2026-03-10T10:00:00Z",
			"createdAt": "2026-01-10T09:00:00Z",
			"updatedAt": "2026-03-10T10:00:00Z"
		},
		{
			"id": "550e8400-e29b-41d4-a716-446655440063",
			"deckId": "550e8400-e29b-41d4-a716-446655440002",
			"front": "Elastic Potential Energy",
			"back": "EPE = ½kx² (elastic potential energy = ½ × spring constant × extension²)",
			"imageUrl": null,
			"difficulty": "medium",
			"timesReviewed": 4,
			"timesCorrect": 3,
			"easeFactor": "2.3",
			"intervalDays": 4,
			"repetitions": 2,
			"nextReview": "2026-03-15T10:00:00Z",
			"lastReview": "2026-03-11T10:00:00Z",
			"createdAt": "2026-01-11T09:00:00Z",
			"updatedAt": "2026-03-11T10:00:00Z"
		},
		{
			"id": "550e8400-e29b-41d4-a716-446655440064",
			"deckId": "550e8400-e29b-41d4-a716-446655440003",
			"front": "Balancing Chemical Equations",
			"back": "Law of Conservation of Mass: atoms cannot be created or destroyed",
			"imageUrl": null,
			"difficulty": "easy",
			"timesReviewed": 8,
			"timesCorrect": 7,
			"easeFactor": "2.7",
			"intervalDays": 10,
			"repetitions": 6,
			"nextReview": "2026-03-20T10:00:00Z",
			"lastReview": "2026-03-10T10:00:00Z",
			"createdAt": "2026-01-03T08:30:00Z",
			"updatedAt": "2026-03-10T10:00:00Z"
		},
		{
			"id": "550e8400-e29b-41d4-a716-446655440065",
			"deckId": "550e8400-e29b-41d4-a716-446655440003",
			"front": "Molarity Formula",
			"back": "M = n/V (Molarity = moles of solute / volume of solution in dm³)",
			"imageUrl": null,
			"difficulty": "easy",
			"timesReviewed": 7,
			"timesCorrect": 6,
			"easeFactor": "2.6",
			"intervalDays": 8,
			"repetitions": 5,
			"nextReview": "2026-03-18T10:00:00Z",
			"lastReview": "2026-03-10T10:00:00Z",
			"createdAt": "2026-01-03T08:30:00Z",
			"updatedAt": "2026-03-10T10:00:00Z"
		},
		{
			"id": "550e8400-e29b-41d4-a716-446655440066",
			"deckId": "550e8400-e29b-41d4-a716-446655440003",
			"front": "Avogadro's Number",
			"back": "6.022 × 10²³ particles per mole",
			"imageUrl": null,
			"difficulty": "easy",
			"timesReviewed": 9,
			"timesCorrect": 8,
			"easeFactor": "2.8",
			"intervalDays": 12,
			"repetitions": 7,
			"nextReview": "2026-03-22T10:00:00Z",
			"lastReview": "2026-03-10T10:00:00Z",
			"createdAt": "2026-01-04T08:30:00Z",
			"updatedAt": "2026-03-10T10:00:00Z"
		},
		{
			"id": "550e8400-e29b-41d4-a716-446655440067",
			"deckId": "550e8400-e29b-41d4-a716-446655440003",
			"front": "Periodic Trend: Electronegativity",
			"back": "Increases from left to right across a period, decreases down a group",
			"imageUrl": null,
			"difficulty": "easy",
			"timesReviewed": 8,
			"timesCorrect": 7,
			"easeFactor": "2.7",
			"intervalDays": 10,
			"repetitions": 6,
			"nextReview": "2026-03-20T10:00:00Z",
			"lastReview": "2026-03-10T10:00:00Z",
			"createdAt": "2026-01-04T08:30:00Z",
			"updatedAt": "2026-03-10T10:00:00Z"
		},
		{
			"id": "550e8400-e29b-41d4-a716-446655440068",
			"deckId": "550e8400-e29b-41d4-a716-446655440003",
			"front": "Ionic Bonding",
			"back": "Transfer of electrons from metal to non-metal, electrostatic attraction",
			"imageUrl": null,
			"difficulty": "easy",
			"timesReviewed": 7,
			"timesCorrect": 6,
			"easeFactor": "2.6",
			"intervalDays": 8,
			"repetitions": 5,
			"nextReview": "2026-03-18T10:00:00Z",
			"lastReview": "2026-03-10T10:00:00Z",
			"createdAt": "2026-01-05T08:30:00Z",
			"updatedAt": "2026-03-10T10:00:00Z"
		},
		{
			"id": "550e8400-e29b-41d4-a716-446655440069",
			"deckId": "550e8400-e29b-41d4-a716-446655440003",
			"front": "Covalent Bonding",
			"back": "Sharing of electron pairs between non-metals",
			"imageUrl": null,
			"difficulty": "easy",
			"timesReviewed": 8,
			"timesCorrect": 7,
			"easeFactor": "2.7",
			"intervalDays": 10,
			"repetitions": 6,
			"nextReview": "2026-03-20T10:00:00Z",
			"lastReview": "2026-03-10T10:00:00Z",
			"createdAt": "2026-01-05T08:30:00Z",
			"updatedAt": "2026-03-10T10:00:00Z"
		},
		{
			"id": "550e8400-e29b-41d4-a716-446655440070",
			"deckId": "550e8400-e29b-41d4-a716-446655440003",
			"front": "Metallic Bonding",
			"back": "Sea of delocalized electrons surrounded by positive metal ions",
			"imageUrl": null,
			"difficulty": "easy",
			"timesReviewed": 7,
			"timesCorrect": 6,
			"easeFactor": "2.6",
			"intervalDays": 8,
			"repetitions": 5,
			"nextReview": "2026-03-18T10:00:00Z",
			"lastReview": "2026-03-10T10:00:00Z",
			"createdAt": "2026-01-05T08:30:00Z",
			"updatedAt": "2026-03-10T10:00:00Z"
		},
		{
			"id": "550e8400-e29b-41d4-a716-446655440071",
			"deckId": "550e8400-e29b-41d4-a716-446655440003",
			"front": "Oxidation Number Rules",
			"back": "Free elements = 0, O = -2, H = +1, metals = positive, sum = 0",
			"imageUrl": null,
			"difficulty": "medium",
			"timesReviewed": 5,
			"timesCorrect": 4,
			"easeFactor": "2.4",
			"intervalDays": 5,
			"repetitions": 3,
			"nextReview": "2026-03-16T10:00:00Z",
			"lastReview": "2026-03-11T10:00:00Z",
			"createdAt": "2026-01-06T08:30:00Z",
			"updatedAt": "2026-03-11T10:00:00Z"
		},
		{
			"id": "550e8400-e29b-41d4-a716-446655440072",
			"deckId": "550e8400-e29b-41d4-a716-446655440003",
			"front": "pH Definition",
			"back": "pH = -log[H⁺] (measure of hydrogen ion concentration)",
			"imageUrl": null,
			"difficulty": "easy",
			"timesReviewed": 9,
			"timesCorrect": 8,
			"easeFactor": "2.8",
			"intervalDays": 12,
			"repetitions": 7,
			"nextReview": "2026-03-22T10:00:00Z",
			"lastReview": "2026-03-10T10:00:00Z",
			"createdAt": "2026-01-06T08:30:00Z",
			"updatedAt": "2026-03-10T10:00:00Z"
		},
		{
			"id": "550e8400-e29b-41d4-a716-446655440073",
			"deckId": "550e8400-e29b-41d4-a716-446655440003",
			"front": "Rate of Reaction Factors",
			"back": "Temperature, concentration, surface area, catalyst, pressure (for gases)",
			"imageUrl": null,
			"difficulty": "easy",
			"timesReviewed": 8,
			"timesCorrect": 7,
			"easeFactor": "2.7",
			"intervalDays": 10,
			"repetitions": 6,
			"nextReview": "2026-03-20T10:00:00Z",
			"lastReview": "2026-03-10T10:00:00Z",
			"createdAt": "2026-01-06T08:30:00Z",
			"updatedAt": "2026-03-10T10:00:00Z"
		},
		{
			"id": "550e8400-e29b-41d4-a716-446655440074",
			"deckId": "550e8400-e29b-41d4-a716-446655440003",
			"front": "Le Chatelier's Principle",
			"back": "System at equilibrium will shift to counteract any change applied",
			"imageUrl": null,
			"difficulty": "medium",
			"timesReviewed": 5,
			"timesCorrect": 4,
			"easeFactor": "2.5",
			"intervalDays": 6,
			"repetitions": 3,
			"nextReview": "2026-03-17T10:00:00Z",
			"lastReview": "2026-03-11T10:00:00Z",
			"createdAt": "2026-01-07T08:30:00Z",
			"updatedAt": "2026-03-11T10:00:00Z"
		},
		{
			"id": "550e8400-e29b-41d4-a716-446655440075",
			"deckId": "550e8400-e29b-41d4-a716-446655440003",
			"front": "Alkanes General Formula",
			"back": "CₙH₂ₙ₊₂ (saturated hydrocarbons with single bonds)",
			"imageUrl": null,
			"difficulty": "easy",
			"timesReviewed": 7,
			"timesCorrect": 6,
			"easeFactor": "2.6",
			"intervalDays": 8,
			"repetitions": 5,
			"nextReview": "2026-03-18T10:00:00Z",
			"lastReview": "2026-03-10T10:00:00Z",
			"createdAt": "2026-01-07T08:30:00Z",
			"updatedAt": "2026-03-10T10:00:00Z"
		},
		{
			"id": "550e8400-e29b-41d4-a716-446655440076",
			"deckId": "550e8400-e29b-41d4-a716-446655440003",
			"front": "Alkenes General Formula",
			"back": "CₙH₂ₙ (unsaturated hydrocarbons with double bond)",
			"imageUrl": null,
			"difficulty": "easy",
			"timesReviewed": 7,
			"timesCorrect": 6,
			"easeFactor": "2.6",
			"intervalDays": 8,
			"repetitions": 5,
			"nextReview": "2026-03-18T10:00:00Z",
			"lastReview": "2026-03-10T10:00:00Z",
			"createdAt": "2026-01-07T08:30:00Z",
			"updatedAt": "2026-03-10T10:00:00Z"
		},
		{
			"id": "550e8400-e29b-41d4-a716-446655440077",
			"deckId": "550e8400-e29b-41d4-a716-446655440003",
			"front": "Addition Reaction",
			"back": "Unsaturated compounds add atoms across double/triple bonds",
			"imageUrl": null,
			"difficulty": "medium",
			"timesReviewed": 4,
			"timesCorrect": 3,
			"easeFactor": "2.3",
			"intervalDays": 4,
			"repetitions": 2,
			"nextReview": "2026-03-15T10:00:00Z",
			"lastReview": "2026-03-11T10:00:00Z",
			"createdAt": "2026-01-08T08:30:00Z",
			"updatedAt": "2026-03-11T10:00:00Z"
		},
		{
			"id": "550e8400-e29b-41d4-a716-446655440078",
			"deckId": "550e8400-e29b-41d4-a716-446655440003",
			"front": "Substitution Reaction",
			"back": "One atom/group replaces another in a molecule",
			"imageUrl": null,
			"difficulty": "medium",
			"timesReviewed": 5,
			"timesCorrect": 4,
			"easeFactor": "2.4",
			"intervalDays": 5,
			"repetitions": 3,
			"nextReview": "2026-03-16T10:00:00Z",
			"lastReview": "2026-03-11T10:00:00Z",
			"createdAt": "2026-01-08T08:30:00Z",
			"updatedAt": "2026-03-11T10:00:00Z"
		},
		{
			"id": "550e8400-e29b-41d4-a716-446655440079",
			"deckId": "550e8400-e29b-41d4-a716-446655440003",
			"front": "Combustion Reaction",
			"back": "Fuel + O₂ → CO₂ + H₂O + energy (complete combustion produces CO₂ and H₂O)",
			"imageUrl": null,
			"difficulty": "easy",
			"timesReviewed": 8,
			"timesCorrect": 7,
			"easeFactor": "2.7",
			"intervalDays": 10,
			"repetitions": 6,
			"nextReview": "2026-03-20T10:00:00Z",
			"lastReview": "2026-03-10T10:00:00Z",
			"createdAt": "2026-01-08T08:30:00Z",
			"updatedAt": "2026-03-10T10:00:00Z"
		},
		{
			"id": "550e8400-e29b-41d4-a716-446655440080",
			"deckId": "550e8400-e29b-41d4-a716-446655440003",
			"front": "Electrolysis",
			"back": "Breaking down of electrolyte using electrical energy",
			"imageUrl": null,
			"difficulty": "medium",
			"timesReviewed": 5,
			"timesCorrect": 4,
			"easeFactor": "2.4",
			"intervalDays": 5,
			"repetitions": 3,
			"nextReview": "2026-03-16T10:00:00Z",
			"lastReview": "2026-03-11T10:00:00Z",
			"createdAt": "2026-01-09T08:30:00Z",
			"updatedAt": "2026-03-11T10:00:00Z"
		},
		{
			"id": "550e8400-e29b-41d4-a716-446655440081",
			"deckId": "550e8400-e29b-41d4-a716-446655440003",
			"front": "Redox Reaction",
			"back": "Simultaneous oxidation (electron loss) and reduction (electron gain)",
			"imageUrl": null,
			"difficulty": "medium",
			"timesReviewed": 5,
			"timesCorrect": 4,
			"easeFactor": "2.4",
			"intervalDays": 5,
			"repetitions": 3,
			"nextReview": "2026-03-16T10:00:00Z",
			"lastReview": "2026-03-11T10:00:00Z",
			"createdAt": "2026-01-09T08:30:00Z",
			"updatedAt": "2026-03-11T10:00:00Z"
		},
		{
			"id": "550e8400-e29b-41d4-a716-446655440082",
			"deckId": "550e8400-e29b-41d4-a716-446655440003",
			"front": "Molar Mass Calculation",
			"back": "Molar mass = sum of atomic masses in the formula",
			"imageUrl": null,
			"difficulty": "easy",
			"timesReviewed": 7,
			"timesCorrect": 6,
			"easeFactor": "2.6",
			"intervalDays": 8,
			"repetitions": 5,
			"nextReview": "2026-03-18T10:00:00Z",
			"lastReview": "2026-03-10T10:00:00Z",
			"createdAt": "2026-01-09T08:30:00Z",
			"updatedAt": "2026-03-10T10:00:00Z"
		},
		{
			"id": "550e8400-e29b-41d4-a716-446655440083",
			"deckId": "550e8400-e29b-41d4-a716-446655440003",
			"front": "Ideal Gas Equation",
			"back": "PV = nRT (Pressure × Volume = moles × gas constant × Temperature)",
			"imageUrl": null,
			"difficulty": "medium",
			"timesReviewed": 5,
			"timesCorrect": 4,
			"easeFactor": "2.4",
			"intervalDays": 5,
			"repetitions": 3,
			"nextReview": "2026-03-16T10:00:00Z",
			"lastReview": "2026-03-11T10:00:00Z",
			"createdAt": "2026-01-10T08:30:00Z",
			"updatedAt": "2026-03-11T10:00:00Z"
		},
		{
			"id": "550e8400-e29b-41d4-a716-446655440084",
			"deckId": "550e8400-e29b-41d4-a716-446655440003",
			"front": "Mole Calculation",
			"back": "n = m/M (moles = mass / molar mass)",
			"imageUrl": null,
			"difficulty": "easy",
			"timesReviewed": 8,
			"timesCorrect": 7,
			"easeFactor": "2.7",
			"intervalDays": 10,
			"repetitions": 6,
			"nextReview": "2026-03-20T10:00:00Z",
			"lastReview": "2026-03-10T10:00:00Z",
			"createdAt": "2026-01-10T08:30:00Z",
			"updatedAt": "2026-03-10T10:00:00Z"
		},
		{
			"id": "550e8400-e29b-41d4-a716-446655440085",
			"deckId": "550e8400-e29b-41d4-a716-446655440003",
			"front": "Percentage Composition",
			"back": "% element = (atomic mass × number of atoms / molar mass) × 100",
			"imageUrl": null,
			"difficulty": "medium",
			"timesReviewed": 5,
			"timesCorrect": 4,
			"easeFactor": "2.4",
			"intervalDays": 5,
			"repetitions": 3,
			"nextReview": "2026-03-16T10:00:00Z",
			"lastReview": "2026-03-11T10:00:00Z",
			"createdAt": "2026-01-10T08:30:00Z",
			"updatedAt": "2026-03-11T10:00:00Z"
		},
		{
			"id": "550e8400-e29b-41d4-a716-446655440086",
			"deckId": "550e8400-e29b-41d4-a716-446655440003",
			"front": "Empirical Formula",
			"back": "Simplest whole number ratio of atoms in a compound",
			"imageUrl": null,
			"difficulty": "medium",
			"timesReviewed": 5,
			"timesCorrect": 4,
			"easeFactor": "2.4",
			"intervalDays": 5,
			"repetitions": 3,
			"nextReview": "2026-03-16T10:00:00Z",
			"lastReview": "2026-03-11T10:00:00Z",
			"createdAt": "2026-01-11T08:30:00Z",
			"updatedAt": "2026-03-11T10:00:00Z"
		},
		{
			"id": "550e8400-e29b-41d4-a716-446655440087",
			"deckId": "550e8400-e29b-41d4-a716-446655440003",
			"front": "Molecular Formula",
			"back": "Actual number of atoms in a molecule (multiple of empirical formula)",
			"imageUrl": null,
			"difficulty": "medium",
			"timesReviewed": 5,
			"timesCorrect": 4,
			"easeFactor": "2.4",
			"intervalDays": 5,
			"repetitions": 3,
			"nextReview": "2026-03-16T10:00:00Z",
			"lastReview": "2026-03-11T10:00:00Z",
			"createdAt": "2026-01-11T08:30:00Z",
			"updatedAt": "2026-03-11T10:00:00Z"
		},
		{
			"id": "550e8400-e29b-41d4-a716-446655440088",
			"deckId": "550e8400-e29b-41d4-a716-446655440003",
			"front": "Enthalpy Change",
			"back": "ΔH = H_products - H_reactants (heat absorbed/released in reaction)",
			"imageUrl": null,
			"difficulty": "medium",
			"timesReviewed": 4,
			"timesCorrect": 3,
			"easeFactor": "2.3",
			"intervalDays": 4,
			"repetitions": 2,
			"nextReview": "2026-03-15T10:00:00Z",
			"lastReview": "2026-03-11T10:00:00Z",
			"createdAt": "2026-01-11T08:30:00Z",
			"updatedAt": "2026-03-11T10:00:00Z"
		},
		{
			"id": "550e8400-e29b-41d4-a716-446655440089",
			"deckId": "550e8400-e29b-41d4-a716-446655440003",
			"front": "Activation Energy",
			"back": "Minimum energy required for a reaction to occur",
			"imageUrl": null,
			"difficulty": "easy",
			"timesReviewed": 7,
			"timesCorrect": 6,
			"easeFactor": "2.6",
			"intervalDays": 8,
			"repetitions": 5,
			"nextReview": "2026-03-18T10:00:00Z",
			"lastReview": "2026-03-10T10:00:00Z",
			"createdAt": "2026-01-12T08:30:00Z",
			"updatedAt": "2026-03-10T10:00:00Z"
		},
		{
			"id": "550e8400-e29b-41d4-a716-446655440090",
			"deckId": "550e8400-e29b-41d4-a716-446655440003",
			"front": "Catalyst",
			"back": "Substance that lowers activation energy without being consumed",
			"imageUrl": null,
			"difficulty": "easy",
			"timesReviewed": 8,
			"timesCorrect": 7,
			"easeFactor": "2.7",
			"intervalDays": 10,
			"repetitions": 6,
			"nextReview": "2026-03-20T10:00:00Z",
			"lastReview": "2026-03-10T10:00:00Z",
			"createdAt": "2026-01-12T08:30:00Z",
			"updatedAt": "2026-03-10T10:00:00Z"
		},
		{
			"id": "550e8400-e29b-41d4-a716-446655440091",
			"deckId": "550e8400-e29b-41d4-a716-446655440004",
			"front": "Mitochondria Function",
			"back": "Site of cellular respiration, produces ATP (the powerhouse of the cell)",
			"imageUrl": null,
			"difficulty": "easy",
			"timesReviewed": 9,
			"timesCorrect": 8,
			"easeFactor": "2.8",
			"intervalDays": 12,
			"repetitions": 7,
			"nextReview": "2026-03-22T10:00:00Z",
			"lastReview": "2026-03-10T10:00:00Z",
			"createdAt": "2026-01-04T12:00:00Z",
			"updatedAt": "2026-03-10T10:00:00Z"
		},
		{
			"id": "550e8400-e29b-41d4-a716-446655440092",
			"deckId": "550e8400-e29b-41d4-a716-446655440004",
			"front": "Nucleus Function",
			"back": "Contains DNA, controls cell activities and reproduction",
			"imageUrl": null,
			"difficulty": "easy",
			"timesReviewed": 8,
			"timesCorrect": 7,
			"easeFactor": "2.7",
			"intervalDays": 10,
			"repetitions": 6,
			"nextReview": "2026-03-20T10:00:00Z",
			"lastReview": "2026-03-10T10:00:00Z",
			"createdAt": "2026-01-04T12:00:00Z",
			"updatedAt": "2026-03-10T10:00:00Z"
		},
		{
			"id": "550e8400-e29b-41d4-a716-446655440093",
			"deckId": "550e8400-e29b-41d4-a716-446655440004",
			"front": "Ribosome Function",
			"back": "Site of protein synthesis (translation)",
			"imageUrl": null,
			"difficulty": "easy",
			"timesReviewed": 7,
			"timesCorrect": 6,
			"easeFactor": "2.6",
			"intervalDays": 8,
			"repetitions": 5,
			"nextReview": "2026-03-18T10:00:00Z",
			"lastReview": "2026-03-10T10:00:00Z",
			"createdAt": "2026-01-05T12:00:00Z",
			"updatedAt": "2026-03-10T10:00:00Z"
		},
		{
			"id": "550e8400-e29b-41d4-a716-446655440094",
			"deckId": "550e8400-e29b-41d4-a716-446655440004",
			"front": "Cell Membrane Structure",
			"back": "Phospholipid bilayer with embedded proteins (fluid mosaic model)",
			"imageUrl": null,
			"difficulty": "easy",
			"timesReviewed": 8,
			"timesCorrect": 7,
			"easeFactor": "2.7",
			"intervalDays": 10,
			"repetitions": 6,
			"nextReview": "2026-03-20T10:00:00Z",
			"lastReview": "2026-03-10T10:00:00Z",
			"createdAt": "2026-01-05T12:00:00Z",
			"updatedAt": "2026-03-10T10:00:00Z"
		},
		{
			"id": "550e8400-e29b-41d4-a716-446655440095",
			"deckId": "550e8400-e29b-41d4-a716-446655440004",
			"front": "Prophase (Mitosis)",
			"back": "Chromatin condenses into chromosomes, nuclear envelope breaks down",
			"imageUrl": null,
			"difficulty": "easy",
			"timesReviewed": 7,
			"timesCorrect": 6,
			"easeFactor": "2.6",
			"intervalDays": 8,
			"repetitions": 5,
			"nextReview": "2026-03-18T10:00:00Z",
			"lastReview": "2026-03-10T10:00:00Z",
			"createdAt": "2026-01-06T12:00:00Z",
			"updatedAt": "2026-03-10T10:00:00Z"
		},
		{
			"id": "550e8400-e29b-41d4-a716-446655440096",
			"deckId": "550e8400-e29b-41d4-a716-446655440004",
			"front": "Metaphase (Mitosis)",
			"back": "Chromosomes align at the cell equator, spindle fibers attach",
			"imageUrl": null,
			"difficulty": "easy",
			"timesReviewed": 7,
			"timesCorrect": 6,
			"easeFactor": "2.6",
			"intervalDays": 8,
			"repetitions": 5,
			"nextReview": "2026-03-18T10:00:00Z",
			"lastReview": "2026-03-10T10:00:00Z",
			"createdAt": "2026-01-06T12:00:00Z",
			"updatedAt": "2026-03-10T10:00:00Z"
		},
		{
			"id": "550e8400-e29b-41d4-a716-446655440097",
			"deckId": "550e8400-e29b-41d4-a716-446655440004",
			"front": "Anaphase (Mitosis)",
			"back": "Sister chromatids separate and move to opposite poles",
			"imageUrl": null,
			"difficulty": "easy",
			"timesReviewed": 7,
			"timesCorrect": 6,
			"easeFactor": "2.6",
			"intervalDays": 8,
			"repetitions": 5,
			"nextReview": "2026-03-18T10:00:00Z",
			"lastReview": "2026-03-10T10:00:00Z",
			"createdAt": "2026-01-06T12:00:00Z",
			"updatedAt": "2026-03-10T10:00:00Z"
		},
		{
			"id": "550e8400-e29b-41d4-a716-446655440098",
			"deckId": "550e8400-e29b-41d4-a716-446655440004",
			"front": "Telophase (Mitosis)",
			"back": "Nuclear envelopes reform, chromosomes uncoil, cytoplasm divides",
			"imageUrl": null,
			"difficulty": "easy",
			"timesReviewed": 7,
			"timesCorrect": 6,
			"easeFactor": "2.6",
			"intervalDays": 8,
			"repetitions": 5,
			"nextReview": "2026-03-18T10:00:00Z",
			"lastReview": "2026-03-10T10:00:00Z",
			"createdAt": "2026-01-07T12:00:00Z",
			"updatedAt": "2026-03-10T10:00:00Z"
		},
		{
			"id": "550e8400-e29b-41d4-a716-446655440099",
			"deckId": "550e8400-e29b-41d4-a716-446655440004",
			"front": "DNA Structure",
			"back": "Double helix, antiparallel strands, complementary base pairing (A-T, G-C)",
			"imageUrl": null,
			"difficulty": "medium",
			"timesReviewed": 5,
			"timesCorrect": 4,
			"easeFactor": "2.5",
			"intervalDays": 6,
			"repetitions": 3,
			"nextReview": "2026-03-17T10:00:00Z",
			"lastReview": "2026-03-11T10:00:00Z",
			"createdAt": "2026-01-07T12:00:00Z",
			"updatedAt": "2026-03-11T10:00:00Z"
		},
		{
			"id": "550e8400-e29b-41d4-a716-446655440100",
			"deckId": "550e8400-e29b-41d4-a716-446655440004",
			"front": "RNA Types",
			"back": "mRNA (messenger), tRNA (transfer), rRNA (ribosomal)",
			"imageUrl": null,
			"difficulty": "medium",
			"timesReviewed": 5,
			"timesCorrect": 4,
			"easeFactor": "2.4",
			"intervalDays": 5,
			"repetitions": 3,
			"nextReview": "2026-03-16T10:00:00Z",
			"lastReview": "2026-03-11T10:00:00Z",
			"createdAt": "2026-01-07T12:00:00Z",
			"updatedAt": "2026-03-11T10:00:00Z"
		},
		{
			"id": "550e8400-e29b-41d4-a716-446655440101",
			"deckId": "550e8400-e29b-41d4-a716-446655440004",
			"front": "DNA Replication",
			"back": "Semi-conservative, DNA polymerase adds nucleotides 5' to 3'",
			"imageUrl": null,
			"difficulty": "medium",
			"timesReviewed": 5,
			"timesCorrect": 4,
			"easeFactor": "2.4",
			"intervalDays": 5,
			"repetitions": 3,
			"nextReview": "2026-03-16T10:00:00Z",
			"lastReview": "2026-03-11T10:00:00Z",
			"createdAt": "2026-01-08T12:00:00Z",
			"updatedAt": "2026-03-11T10:00:00Z"
		},
		{
			"id": "550e8400-e29b-41d4-a716-446655440102",
			"deckId": "550e8400-e29b-41d4-a716-446655440004",
			"front": "Transcription",
			"back": "DNA sequence copied to mRNA in the nucleus",
			"imageUrl": null,
			"difficulty": "medium",
			"timesReviewed": 5,
			"timesCorrect": 4,
			"easeFactor": "2.4",
			"intervalDays": 5,
			"repetitions": 3,
			"nextReview": "2026-03-16T10:00:00Z",
			"lastReview": "2026-03-11T10:00:00Z",
			"createdAt": "2026-01-08T12:00:00Z",
			"updatedAt": "2026-03-11T10:00:00Z"
		},
		{
			"id": "550e8400-e29b-41d4-a716-446655440103",
			"deckId": "550e8400-e29b-41d4-a716-446655440004",
			"front": "Translation",
			"back": "mRNA code read at ribosome to build protein (amino acid sequence)",
			"imageUrl": null,
			"difficulty": "medium",
			"timesReviewed": 5,
			"timesCorrect": 4,
			"easeFactor": "2.4",
			"intervalDays": 5,
			"repetitions": 3,
			"nextReview": "2026-03-16T10:00:00Z",
			"lastReview": "2026-03-11T10:00:00Z",
			"createdAt": "2026-01-08T12:00:00Z",
			"updatedAt": "2026-03-11T10:00:00Z"
		},
		{
			"id": "550e8400-e29b-41d4-a716-446655440104",
			"deckId": "550e8400-e29b-41d4-a716-446655440004",
			"front": "Mendel's First Law (Segregation)",
			"back": "Allele pairs separate during gamete formation",
			"imageUrl": null,
			"difficulty": "easy",
			"timesReviewed": 8,
			"timesCorrect": 7,
			"easeFactor": "2.7",
			"intervalDays": 10,
			"repetitions": 6,
			"nextReview": "2026-03-20T10:00:00Z",
			"lastReview": "2026-03-10T10:00:00Z",
			"createdAt": "2026-01-09T12:00:00Z",
			"updatedAt": "2026-03-10T10:00:00Z"
		},
		{
			"id": "550e8400-e29b-41d4-a716-446655440105",
			"deckId": "550e8400-e29b-41d4-a716-446655440004",
			"front": "Mendel's Second Law (Independent Assortment)",
			"back": "Genes for different traits assort independently during gamete formation",
			"imageUrl": null,
			"difficulty": "easy",
			"timesReviewed": 7,
			"timesCorrect": 6,
			"easeFactor": "2.6",
			"intervalDays": 8,
			"repetitions": 5,
			"nextReview": "2026-03-18T10:00:00Z",
			"lastReview": "2026-03-10T10:00:00Z",
			"createdAt": "2026-01-09T12:00:00Z",
			"updatedAt": "2026-03-10T10:00:00Z"
		},
		{
			"id": "550e8400-e29b-41d4-a716-446655440106",
			"deckId": "550e8400-e29b-41d4-a716-446655440004",
			"front": "Dominant Allele",
			"back": "Allele that masks the recessive allele, expressed in heterozygotes",
			"imageUrl": null,
			"difficulty": "easy",
			"timesReviewed": 8,
			"timesCorrect": 7,
			"easeFactor": "2.7",
			"intervalDays": 10,
			"repetitions": 6,
			"nextReview": "2026-03-20T10:00:00Z",
			"lastReview": "2026-03-10T10:00:00Z",
			"createdAt": "2026-01-09T12:00:00Z",
			"updatedAt": "2026-03-10T10:00:00Z"
		},
		{
			"id": "550e8400-e29b-41d4-a716-446655440107",
			"deckId": "550e8400-e29b-41d4-a716-446655440004",
			"front": "Recessive Allele",
			"back": "Allele masked by dominant allele, only expressed in homozygotes",
			"imageUrl": null,
			"difficulty": "easy",
			"timesReviewed": 8,
			"timesCorrect": 7,
			"easeFactor": "2.7",
			"intervalDays": 10,
			"repetitions": 6,
			"nextReview": "2026-03-20T10:00:00Z",
			"lastReview": "2026-03-10T10:00:00Z",
			"createdAt": "2026-01-10T12:00:00Z",
			"updatedAt": "2026-03-10T10:00:00Z"
		},
		{
			"id": "550e8400-e29b-41d4-a716-446655440108",
			"deckId": "550e8400-e29b-41d4-a716-446655440004",
			"front": "Codominance",
			"back": "Both alleles expressed equally in heterozygote (e.g., AB blood type)",
			"imageUrl": null,
			"difficulty": "medium",
			"timesReviewed": 5,
			"timesCorrect": 4,
			"easeFactor": "2.4",
			"intervalDays": 5,
			"repetitions": 3,
			"nextReview": "2026-03-16T10:00:00Z",
			"lastReview": "2026-03-11T10:00:00Z",
			"createdAt": "2026-01-10T12:00:00Z",
			"updatedAt": "2026-03-11T10:00:00Z"
		},
		{
			"id": "550e8400-e29b-41d4-a716-446655440109",
			"deckId": "550e8400-e29b-41d4-a716-446655440004",
			"front": "Incomplete Dominance",
			"back": "Heterozygote shows intermediate phenotype (e.g., pink snapdragons)",
			"imageUrl": null,
			"difficulty": "medium",
			"timesReviewed": 5,
			"timesCorrect": 4,
			"easeFactor": "2.4",
			"intervalDays": 5,
			"repetitions": 3,
			"nextReview": "2026-03-16T10:00:00Z",
			"lastReview": "2026-03-11T10:00:00Z",
			"createdAt": "2026-01-10T12:00:00Z",
			"updatedAt": "2026-03-11T10:00:00Z"
		},
		{
			"id": "550e8400-e29b-41d4-a716-446655440110",
			"deckId": "550e8400-e29b-41d4-a716-446655440004",
			"front": "Natural Selection",
			"back": "Organisms with favorable traits survive and reproduce more successfully",
			"imageUrl": null,
			"difficulty": "easy",
			"timesReviewed": 8,
			"timesCorrect": 7,
			"easeFactor": "2.7",
			"intervalDays": 10,
			"repetitions": 6,
			"nextReview": "2026-03-20T10:00:00Z",
			"lastReview": "2026-03-10T10:00:00Z",
			"createdAt": "2026-01-11T12:00:00Z",
			"updatedAt": "2026-03-10T10:00:00Z"
		},
		{
			"id": "550e8400-e29b-41d4-a716-446655440111",
			"deckId": "550e8400-e29b-41d4-a716-446655440004",
			"front": "Evolution",
			"back": "Change in inherited characteristics of a population over time",
			"imageUrl": null,
			"difficulty": "easy",
			"timesReviewed": 7,
			"timesCorrect": 6,
			"easeFactor": "2.6",
			"intervalDays": 8,
			"repetitions": 5,
			"nextReview": "2026-03-18T10:00:00Z",
			"lastReview": "2026-03-10T10:00:00Z",
			"createdAt": "2026-01-11T12:00:00Z",
			"updatedAt": "2026-03-10T10:00:00Z"
		},
		{
			"id": "550e8400-e29b-41d4-a716-446655440112",
			"deckId": "550e8400-e29b-41d4-a716-446655440004",
			"front": "Speciation",
			"back": "Formation of new species through evolution",
			"imageUrl": null,
			"difficulty": "easy",
			"timesReviewed": 7,
			"timesCorrect": 6,
			"easeFactor": "2.6",
			"intervalDays": 8,
			"repetitions": 5,
			"nextReview": "2026-03-18T10:00:00Z",
			"lastReview": "2026-03-10T10:00:00Z",
			"createdAt": "2026-01-11T12:00:00Z",
			"updatedAt": "2026-03-10T10:00:00Z"
		},
		{
			"id": "550e8400-e29b-41d4-a716-446655440113",
			"deckId": "550e8400-e29b-41d4-a716-446655440004",
			"front": "Photosynthesis Equation",
			"back": "6CO₂ + 6H₂O + light → C₆H₁₂O₆ + 6O₂",
			"imageUrl": null,
			"difficulty": "easy",
			"timesReviewed": 8,
			"timesCorrect": 7,
			"easeFactor": "2.7",
			"intervalDays": 10,
			"repetitions": 6,
			"nextReview": "2026-03-20T10:00:00Z",
			"lastReview": "2026-03-10T10:00:00Z",
			"createdAt": "2026-01-12T12:00:00Z",
			"updatedAt": "2026-03-10T10:00:00Z"
		},
		{
			"id": "550e8400-e29b-41d4-a716-446655440114",
			"deckId": "550e8400-e29b-41d4-a716-446655440004",
			"front": "Cellular Respiration Equation",
			"back": "C₆H₁₂O₆ + 6O₂ → 6CO₂ + 6H₂O + ATP",
			"imageUrl": null,
			"difficulty": "easy",
			"timesReviewed": 8,
			"timesCorrect": 7,
			"easeFactor": "2.7",
			"intervalDays": 10,
			"repetitions": 6,
			"nextReview": "2026-03-20T10:00:00Z",
			"lastReview": "2026-03-10T10:00:00Z",
			"createdAt": "2026-01-12T12:00:00Z",
			"updatedAt": "2026-03-10T10:00:00Z"
		},
		{
			"id": "550e8400-e29b-41d4-a716-446655440115",
			"deckId": "550e8400-e29b-41d4-a716-446655440004",
			"front": "Chloroplast Function",
			"back": "Site of photosynthesis, contains chlorophyll",
			"imageUrl": null,
			"difficulty": "easy",
			"timesReviewed": 9,
			"timesCorrect": 8,
			"easeFactor": "2.8",
			"intervalDays": 12,
			"repetitions": 7,
			"nextReview": "2026-03-22T10:00:00Z",
			"lastReview": "2026-03-10T10:00:00Z",
			"createdAt": "2026-01-12T12:00:00Z",
			"updatedAt": "2026-03-10T10:00:00Z"
		},
		{
			"id": "550e8400-e29b-41d4-a716-446655440116",
			"deckId": "550e8400-e29b-41d4-a716-446655440005",
			"front": "Metaphor",
			"back": "Direct comparison without using 'like' or 'as' (e.g., 'All the world's a stage')",
			"imageUrl": null,
			"difficulty": "easy",
			"timesReviewed": 8,
			"timesCorrect": 7,
			"easeFactor": "2.7",
			"intervalDays": 10,
			"repetitions": 6,
			"nextReview": "2026-03-20T10:00:00Z",
			"lastReview": "2026-03-10T10:00:00Z",
			"createdAt": "2026-01-05T14:00:00Z",
			"updatedAt": "2026-03-10T10:00:00Z"
		},
		{
			"id": "550e8400-e29b-41d4-a716-446655440117",
			"deckId": "550e8400-e29b-41d4-a716-446655440005",
			"front": "Simile",
			"back": "Comparison using 'like' or 'as' (e.g., 'brave as a lion')",
			"imageUrl": null,
			"difficulty": "easy",
			"timesReviewed": 8,
			"timesCorrect": 7,
			"easeFactor": "2.7",
			"intervalDays": 10,
			"repetitions": 6,
			"nextReview": "2026-03-20T10:00:00Z",
			"lastReview": "2026-03-10T10:00:00Z",
			"createdAt": "2026-01-05T14:00:00Z",
			"updatedAt": "2026-03-10T10:00:00Z"
		},
		{
			"id": "550e8400-e29b-41d4-a716-446655440118",
			"deckId": "550e8400-e29b-41d4-a716-446655440005",
			"front": "Personification",
			"back": "Giving human traits to non-human things",
			"imageUrl": null,
			"difficulty": "easy",
			"timesReviewed": 7,
			"timesCorrect": 6,
			"easeFactor": "2.6",
			"intervalDays": 8,
			"repetitions": 5,
			"nextReview": "2026-03-18T10:00:00Z",
			"lastReview": "2026-03-10T10:00:00Z",
			"createdAt": "2026-01-06T14:00:00Z",
			"updatedAt": "2026-03-10T10:00:00Z"
		},
		{
			"id": "550e8400-e29b-41d4-a716-446655440119",
			"deckId": "550e8400-e29b-41d4-a716-446655440005",
			"front": "Alliteration",
			"back": "Repetition of consonant sounds at the start of words (e.g., 'Sally sells seashells')",
			"imageUrl": null,
			"difficulty": "easy",
			"timesReviewed": 7,
			"timesCorrect": 6,
			"easeFactor": "2.6",
			"intervalDays": 8,
			"repetitions": 5,
			"nextReview": "2026-03-18T10:00:00Z",
			"lastReview": "2026-03-10T10:00:00Z",
			"createdAt": "2026-01-06T14:00:00Z",
			"updatedAt": "2026-03-10T10:00:00Z"
		},
		{
			"id": "550e8400-e29b-41d4-a716-446655440120",
			"deckId": "550e8400-e29b-41d4-a716-446655440005",
			"front": "Hyperbole",
			"back": "Exaggeration for emphasis or effect (e.g., 'I'm so hungry I could eat a horse')",
			"imageUrl": null,
			"difficulty": "easy",
			"timesReviewed": 7,
			"timesCorrect": 6,
			"easeFactor": "2.6",
			"intervalDays": 8,
			"repetitions": 5,
			"nextReview": "2026-03-18T10:00:00Z",
			"lastReview": "2026-03-10T10:00:00Z",
			"createdAt": "2026-01-06T14:00:00Z",
			"updatedAt": "2026-03-10T10:00:00Z"
		},
		{
			"id": "550e8400-e29b-41d4-a716-446655440121",
			"deckId": "550e8400-e29b-41d4-a716-446655440005",
			"front": "Onomatopoeia",
			"back": "Words that imitate sounds (e.g., 'buzz', 'hiss', 'crash')",
			"imageUrl": null,
			"difficulty": "easy",
			"timesReviewed": 7,
			"timesCorrect": 6,
			"easeFactor": "2.6",
			"intervalDays": 8,
			"repetitions": 5,
			"nextReview": "2026-03-18T10:00:00Z",
			"lastReview": "2026-03-10T10:00:00Z",
			"createdAt": "2026-01-07T14:00:00Z",
			"updatedAt": "2026-03-10T10:00:00Z"
		},
		{
			"id": "550e8400-e29b-41d4-a716-446655440122",
			"deckId": "550e8400-e29b-41d4-a716-446655440005",
			"front": "Irony",
			"back": "Contrast between expectation and reality (verbal, dramatic, or situational)",
			"imageUrl": null,
			"difficulty": "medium",
			"timesReviewed": 5,
			"timesCorrect": 4,
			"easeFactor": "2.4",
			"intervalDays": 5,
			"repetitions": 3,
			"nextReview": "2026-03-16T10:00:00Z",
			"lastReview": "2026-03-11T10:00:00Z",
			"createdAt": "2026-01-07T14:00:00Z",
			"updatedAt": "2026-03-11T10:00:00Z"
		},
		{
			"id": "550e8400-e29b-41d4-a716-446655440123",
			"deckId": "550e8400-e29b-41d4-a716-446655440005",
			"front": "Theme",
			"back": "Central idea or message of a literary work",
			"imageUrl": null,
			"difficulty": "easy",
			"timesReviewed": 8,
			"timesCorrect": 7,
			"easeFactor": "2.7",
			"intervalDays": 10,
			"repetitions": 6,
			"nextReview": "2026-03-20T10:00:00Z",
			"lastReview": "2026-03-10T10:00:00Z",
			"createdAt": "2026-01-07T14:00:00Z",
			"updatedAt": "2026-03-10T10:00:00Z"
		},
		{
			"id": "550e8400-e29b-41d4-a716-446655440124",
			"deckId": "550e8400-e29b-41d4-a716-446655440005",
			"front": "Motif",
			"back": "Recurring element that contributes to the theme",
			"imageUrl": null,
			"difficulty": "medium",
			"timesReviewed": 5,
			"timesCorrect": 4,
			"easeFactor": "2.4",
			"intervalDays": 5,
			"repetitions": 3,
			"nextReview": "2026-03-16T10:00:00Z",
			"lastReview": "2026-03-11T10:00:00Z",
			"createdAt": "2026-01-08T14:00:00Z",
			"updatedAt": "2026-03-11T10:00:00Z"
		},
		{
			"id": "550e8400-e29b-41d4-a716-446655440125",
			"deckId": "550e8400-e29b-41d4-a716-446655440005",
			"front": "Narrator",
			"back": "Person telling the story (first person, third person limited, omniscient)",
			"imageUrl": null,
			"difficulty": "easy",
			"timesReviewed": 7,
			"timesCorrect": 6,
			"easeFactor": "2.6",
			"intervalDays": 8,
			"repetitions": 5,
			"nextReview": "2026-03-18T10:00:00Z",
			"lastReview": "2026-03-10T10:00:00Z",
			"createdAt": "2026-01-08T14:00:00Z",
			"updatedAt": "2026-03-10T10:00:00Z"
		},
		{
			"id": "550e8400-e29b-41d4-a716-446655440126",
			"deckId": "550e8400-e29b-41d4-a716-446655440005",
			"front": "Foil",
			"back": "Character who contrasts with main character to highlight traits",
			"imageUrl": null,
			"difficulty": "medium",
			"timesReviewed": 5,
			"timesCorrect": 4,
			"easeFactor": "2.4",
			"intervalDays": 5,
			"repetitions": 3,
			"nextReview": "2026-03-16T10:00:00Z",
			"lastReview": "2026-03-11T10:00:00Z",
			"createdAt": "2026-01-08T14:00:00Z",
			"updatedAt": "2026-03-11T10:00:00Z"
		},
		{
			"id": "550e8400-e29b-41d4-a716-446655440127",
			"deckId": "550e8400-e29b-41d4-a716-446655440005",
			"front": "Protagonist",
			"back": "Main character in a story",
			"imageUrl": null,
			"difficulty": "easy",
			"timesReviewed": 8,
			"timesCorrect": 7,
			"easeFactor": "2.7",
			"intervalDays": 10,
			"repetitions": 6,
			"nextReview": "2026-03-20T10:00:00Z",
			"lastReview": "2026-03-10T10:00:00Z",
			"createdAt": "2026-01-09T14:00:00Z",
			"updatedAt": "2026-03-10T10:00:00Z"
		},
		{
			"id": "550e8400-e29b-41d4-a716-446655440128",
			"deckId": "550e8400-e29b-41d4-a716-446655440005",
			"front": "Antagonist",
			"back": "Character opposing the protagonist",
			"imageUrl": null,
			"difficulty": "easy",
			"timesReviewed": 8,
			"timesCorrect": 7,
			"easeFactor": "2.7",
			"intervalDays": 10,
			"repetitions": 6,
			"nextReview": "2026-03-20T10:00:00Z",
			"lastReview": "2026-03-10T10:00:00Z",
			"createdAt": "2026-01-09T14:00:00Z",
			"updatedAt": "2026-03-10T10:00:00Z"
		},
		{
			"id": "550e8400-e29b-41d4-a716-446655440129",
			"deckId": "550e8400-e29b-41d4-a716-446655440005",
			"front": "Thesis Statement",
			"back": "Main argument of an essay, usually in the introduction",
			"imageUrl": null,
			"difficulty": "easy",
			"timesReviewed": 7,
			"timesCorrect": 6,
			"easeFactor": "2.6",
			"intervalDays": 8,
			"repetitions": 5,
			"nextReview": "2026-03-18T10:00:00Z",
			"lastReview": "2026-03-10T10:00:00Z",
			"createdAt": "2026-01-09T14:00:00Z",
			"updatedAt": "2026-03-10T10:00:00Z"
		},
		{
			"id": "550e8400-e29b-41d4-a716-446655440130",
			"deckId": "550e8400-e29b-41d4-a716-446655440005",
			"front": "PEE Paragraph Structure",
			"back": "Point, Evidence, Explanation - organize paragraph arguments",
			"imageUrl": null,
			"difficulty": "medium",
			"timesReviewed": 5,
			"timesCorrect": 4,
			"easeFactor": "2.4",
			"intervalDays": 5,
			"repetitions": 3,
			"nextReview": "2026-03-16T10:00:00Z",
			"lastReview": "2026-03-11T10:00:00Z",
			"createdAt": "2026-01-10T14:00:00Z",
			"updatedAt": "2026-03-11T10:00:00Z"
		},
		{
			"id": "550e8400-e29b-41d4-a716-446655440131",
			"deckId": "550e8400-e29b-41d4-a716-446655440005",
			"front": "Symbolism",
			"back": "Using objects to represent ideas or qualities",
			"imageUrl": null,
			"difficulty": "easy",
			"timesReviewed": 7,
			"timesCorrect": 6,
			"easeFactor": "2.6",
			"intervalDays": 8,
			"repetitions": 5,
			"nextReview": "2026-03-18T10:00:00Z",
			"lastReview": "2026-03-10T10:00:00Z",
			"createdAt": "2026-01-10T14:00:00Z",
			"updatedAt": "2026-03-10T10:00:00Z"
		},
		{
			"id": "550e8400-e29b-41d4-a716-446655440132",
			"deckId": "550e8400-e29b-41d4-a716-446655440005",
			"front": "Allegory",
			"back": "Story with hidden meaning, often political or moral",
			"imageUrl": null,
			"difficulty": "medium",
			"timesReviewed": 5,
			"timesCorrect": 4,
			"easeFactor": "2.4",
			"intervalDays": 5,
			"repetitions": 3,
			"nextReview": "2026-03-16T10:00:00Z",
			"lastReview": "2026-03-11T10:00:00Z",
			"createdAt": "2026-01-11T14:00:00Z",
			"updatedAt": "2026-03-11T10:00:00Z"
		},
		{
			"id": "550e8400-e29b-41d4-a716-446655440133",
			"deckId": "550e8400-e29b-41d4-a716-446655440005",
			"front": "Foreshadowing",
			"back": "Hints about future events in the story",
			"imageUrl": null,
			"difficulty": "easy",
			"timesReviewed": 7,
			"timesCorrect": 6,
			"easeFactor": "2.6",
			"intervalDays": 8,
			"repetitions": 5,
			"nextReview": "2026-03-18T10:00:00Z",
			"lastReview": "2026-03-10T10:00:00Z",
			"createdAt": "2026-01-11T14:00:00Z",
			"updatedAt": "2026-03-10T10:00:00Z"
		},
		{
			"id": "550e8400-e29b-41d4-a716-446655440134",
			"deckId": "550e8400-e29b-41d4-a716-446655440005",
			"front": "Flashback",
			"back": "Scene from the past interrupting present action",
			"imageUrl": null,
			"difficulty": "easy",
			"timesReviewed": 7,
			"timesCorrect": 6,
			"easeFactor": "2.6",
			"intervalDays": 8,
			"repetitions": 5,
			"nextReview": "2026-03-18T10:00:00Z",
			"lastReview": "2026-03-10T10:00:00Z",
			"createdAt": "2026-01-11T14:00:00Z",
			"updatedAt": "2026-03-10T10:00:00Z"
		},
		{
			"id": "550e8400-e29b-41d4-a716-446655440135",
			"deckId": "550e8400-e29b-41d4-a716-446655440005",
			"front": "Inference",
			"back": "Drawing conclusions based on evidence and reasoning",
			"imageUrl": null,
			"difficulty": "easy",
			"timesReviewed": 7,
			"timesCorrect": 6,
			"easeFactor": "2.6",
			"intervalDays": 8,
			"repetitions": 5,
			"nextReview": "2026-03-18T10:00:00Z",
			"lastReview": "2026-03-10T10:00:00Z",
			"createdAt": "2026-01-12T14:00:00Z",
			"updatedAt": "2026-03-10T10:00:00Z"
		},
		{
			"id": "550e8400-e29b-41d4-a716-446655440136",
			"deckId": "550e8400-e29b-41d4-a716-446655440006",
			"front": "Union of South Africa (1910)",
			"back": "Four British colonies unified, laying foundation for apartheid",
			"imageUrl": null,
			"difficulty": "medium",
			"timesReviewed": 5,
			"timesCorrect": 4,
			"easeFactor": "2.4",
			"intervalDays": 5,
			"repetitions": 3,
			"nextReview": "2026-03-16T10:00:00Z",
			"lastReview": "2026-03-11T10:00:00Z",
			"createdAt": "2026-01-06T11:00:00Z",
			"updatedAt": "2026-03-11T10:00:00Z"
		},
		{
			"id": "550e8400-e29b-41d4-a716-446655440137",
			"deckId": "550e8400-e29b-41d4-a716-446655440006",
			"front": "Apartheid Laws (1948)",
			"back": "System of racial segregation implemented by National Party",
			"imageUrl": null,
			"difficulty": "easy",
			"timesReviewed": 8,
			"timesCorrect": 7,
			"easeFactor": "2.7",
			"intervalDays": 10,
			"repetitions": 6,
			"nextReview": "2026-03-20T10:00:00Z",
			"lastReview": "2026-03-10T10:00:00Z",
			"createdAt": "2026-01-07T11:00:00Z",
			"updatedAt": "2026-03-10T10:00:00Z"
		},
		{
			"id": "550e8400-e29b-41d4-a716-446655440138",
			"deckId": "550e8400-e29b-41d4-a716-446655440006",
			"front": "Sharpeville Massacre (1960)",
			"back": "Police fired on protesters, 69 killed, led to ANC armed struggle",
			"imageUrl": null,
			"difficulty": "easy",
			"timesReviewed": 8,
			"timesCorrect": 7,
			"easeFactor": "2.7",
			"intervalDays": 10,
			"repetitions": 6,
			"nextReview": "2026-03-20T10:00:00Z",
			"lastReview": "2026-03-10T10:00:00Z",
			"createdAt": "2026-01-07T11:00:00Z",
			"updatedAt": "2026-03-10T10:00:00Z"
		},
		{
			"id": "550e8400-e29b-41d4-a716-446655440139",
			"deckId": "550e8400-e29b-41d4-a716-446655440006",
			"front": "Soweto Uprising (1976)",
			"back": "Student protest against Afrikaans medium education, Hector Petersen killed",
			"imageUrl": null,
			"difficulty": "easy",
			"timesReviewed": 8,
			"timesCorrect": 7,
			"easeFactor": "2.7",
			"intervalDays": 10,
			"repetitions": 6,
			"nextReview": "2026-03-20T10:00:00Z",
			"lastReview": "2026-03-10T10:00:00Z",
			"createdAt": "2026-01-08T11:00:00Z",
			"updatedAt": "2026-03-10T10:00:00Z"
		},
		{
			"id": "550e8400-e29b-41d4-a716-446655440140",
			"deckId": "550e8400-e29b-41d4-a716-446655440006",
			"front": "Nelson Mandela",
			"back": "Anti-apartheid leader, imprisoned 27 years, first democratically elected President",
			"imageUrl": null,
			"difficulty": "easy",
			"timesReviewed": 9,
			"timesCorrect": 8,
			"easeFactor": "2.8",
			"intervalDays": 12,
			"repetitions": 7,
			"nextReview": "2026-03-22T10:00:00Z",
			"lastReview": "2026-03-10T10:00:00Z",
			"createdAt": "2026-01-08T11:00:00Z",
			"updatedAt": "2026-03-10T10:00:00Z"
		},
		{
			"id": "550e8400-e29b-41d4-a716-446655440141",
			"deckId": "550e8400-e29b-41d4-a716-446655440006",
			"front": "Steve Biko",
			"back": "Black Consciousness Movement founder, died in police custody 1977",
			"imageUrl": null,
			"difficulty": "medium",
			"timesReviewed": 5,
			"timesCorrect": 4,
			"easeFactor": "2.4",
			"intervalDays": 5,
			"repetitions": 3,
			"nextReview": "2026-03-16T10:00:00Z",
			"lastReview": "2026-03-11T10:00:00Z",
			"createdAt": "2026-01-09T11:00:00Z",
			"updatedAt": "2026-03-11T10:00:00Z"
		},
		{
			"id": "550e8400-e29b-41d4-a716-446655440142",
			"deckId": "550e8400-e29b-41d4-a716-446655440006",
			"front": "CODESA (1991)",
			"back": "Multi-party negotiation forum to end apartheid",
			"imageUrl": null,
			"difficulty": "medium",
			"timesReviewed": 5,
			"timesCorrect": 4,
			"easeFactor": "2.4",
			"intervalDays": 5,
			"repetitions": 3,
			"nextReview": "2026-03-16T10:00:00Z",
			"lastReview": "2026-03-11T10:00:00Z",
			"createdAt": "2026-01-09T11:00:00Z",
			"updatedAt": "2026-03-11T10:00:00Z"
		},
		{
			"id": "550e8400-e29b-41d4-a716-446655440143",
			"deckId": "550e8400-e29b-41d4-a716-446655440006",
			"front": "1994 Elections",
			"back": "First democratic election in South Africa, Mandela elected President",
			"imageUrl": null,
			"difficulty": "easy",
			"timesReviewed": 9,
			"timesCorrect": 8,
			"easeFactor": "2.8",
			"intervalDays": 12,
			"repetitions": 7,
			"nextReview": "2026-03-22T10:00:00Z",
			"lastReview": "2026-03-10T10:00:00Z",
			"createdAt": "2026-01-10T11:00:00Z",
			"updatedAt": "2026-03-10T10:00:00Z"
		},
		{
			"id": "550e8400-e29b-41d4-a716-446655440144",
			"deckId": "550e8400-e29b-41d4-a716-446655440006",
			"front": "World War I (1914-1918)",
			"back": "Global conflict triggered by assassination of Archduke Franz Ferdinand",
			"imageUrl": null,
			"difficulty": "easy",
			"timesReviewed": 7,
			"timesCorrect": 6,
			"easeFactor": "2.6",
			"intervalDays": 8,
			"repetitions": 5,
			"nextReview": "2026-03-18T10:00:00Z",
			"lastReview": "2026-03-10T10:00:00Z",
			"createdAt": "2026-01-10T11:00:00Z",
			"updatedAt": "2026-03-10T10:00:00Z"
		},
		{
			"id": "550e8400-e29b-41d4-a716-446655440145",
			"deckId": "550e8400-e29b-41d4-a716-446655440006",
			"front": "World War II (1939-1945)",
			"back": "Global conflict involving Axis and Allied powers",
			"imageUrl": null,
			"difficulty": "easy",
			"timesReviewed": 7,
			"timesCorrect": 6,
			"easeFactor": "2.6",
			"intervalDays": 8,
			"repetitions": 5,
			"nextReview": "2026-03-18T10:00:00Z",
			"lastReview": "2026-03-10T10:00:00Z",
			"createdAt": "2026-01-10T11:00:00Z",
			"updatedAt": "2026-03-10T10:00:00Z"
		},
		{
			"id": "550e8400-e29b-41d4-a716-446655440146",
			"deckId": "550e8400-e29b-41d4-a716-446655440006",
			"front": "Cold War",
			"back": "Ideological conflict between USA (capitalism) and USSR (communism)",
			"imageUrl": null,
			"difficulty": "easy",
			"timesReviewed": 7,
			"timesCorrect": 6,
			"easeFactor": "2.6",
			"intervalDays": 8,
			"repetitions": 5,
			"nextReview": "2026-03-18T10:00:00Z",
			"lastReview": "2026-03-10T10:00:00Z",
			"createdAt": "2026-01-11T11:00:00Z",
			"updatedAt": "2026-03-10T10:00:00Z"
		},
		{
			"id": "550e8400-e29b-41d4-a716-446655440147",
			"deckId": "550e8400-e29b-41d4-a716-446655440006",
			"front": "Russian Revolution (1917)",
			"back": "Overthrow of Tsarist regime, establishment of Soviet state",
			"imageUrl": null,
			"difficulty": "medium",
			"timesReviewed": 5,
			"timesCorrect": 4,
			"easeFactor": "2.4",
			"intervalDays": 5,
			"repetitions": 3,
			"nextReview": "2026-03-16T10:00:00Z",
			"lastReview": "2026-03-11T10:00:00Z",
			"createdAt": "2026-01-11T11:00:00Z",
			"updatedAt": "2026-03-11T10:00:00Z"
		},
		{
			"id": "550e8400-e29b-41d4-a716-446655440148",
			"deckId": "550e8400-e29b-41d4-a716-446655440006",
			"front": "Indian Independence (1947)",
			"back": "End of British rule, partition into India and Pakistan",
			"imageUrl": null,
			"difficulty": "medium",
			"timesReviewed": 5,
			"timesCorrect": 4,
			"easeFactor": "2.4",
			"intervalDays": 5,
			"repetitions": 3,
			"nextReview": "2026-03-16T10:00:00Z",
			"lastReview": "2026-03-11T10:00:00Z",
			"createdAt": "2026-01-11T11:00:00Z",
			"updatedAt": "2026-03-11T10:00:00Z"
		},
		{
			"id": "550e8400-e29b-41d4-a716-446655440149",
			"deckId": "550e8400-e29b-41d4-a716-446655440006",
			"front": "French Revolution (1789)",
			"back": "Overthrow of monarchy, rise of radical politics in France",
			"imageUrl": null,
			"difficulty": "medium",
			"timesReviewed": 5,
			"timesCorrect": 4,
			"easeFactor": "2.4",
			"intervalDays": 5,
			"repetitions": 3,
			"nextReview": "2026-03-16T10:00:00Z",
			"lastReview": "2026-03-11T10:00:00Z",
			"createdAt": "2026-01-12T11:00:00Z",
			"updatedAt": "2026-03-11T10:00:00Z"
		},
		{
			"id": "550e8400-e29b-41d4-a716-446655440150",
			"deckId": "550e8400-e29b-41d4-a716-446655440006",
			"front": "Pan Africanism",
			"back": "Movement advocating solidarity among African peoples",
			"imageUrl": null,
			"difficulty": "medium",
			"timesReviewed": 5,
			"timesCorrect": 4,
			"easeFactor": "2.4",
			"intervalDays": 5,
			"repetitions": 3,
			"nextReview": "2026-03-16T10:00:00Z",
			"lastReview": "2026-03-11T10:00:00Z",
			"createdAt": "2026-01-12T11:00:00Z",
			"updatedAt": "2026-03-11T10:00:00Z"
		},
		{
			"id": "550e8400-e29b-41d4-a716-446655440151",
			"deckId": "550e8400-e29b-41d4-a716-446655440006",
			"front": "African National Congress (ANC)",
			"back": "Founded 1912, led anti-apartheid struggle",
			"imageUrl": null,
			"difficulty": "easy",
			"timesReviewed": 8,
			"timesCorrect": 7,
			"easeFactor": "2.7",
			"intervalDays": 10,
			"repetitions": 6,
			"nextReview": "2026-03-20T10:00:00Z",
			"lastReview": "2026-03-10T10:00:00Z",
			"createdAt": "2026-01-12T11:00:00Z",
			"updatedAt": "2026-03-10T10:00:00Z"
		},
		{
			"id": "550e8400-e29b-41d4-a716-446655440152",
			"deckId": "550e8400-e29b-41d4-a716-446655440006",
			"front": "Truth and Reconciliation Commission",
			"back": "1995-1996, chaired by Desmond Tutu, addressed apartheid human rights violations",
			"imageUrl": null,
			"difficulty": "medium",
			"timesReviewed": 5,
			"timesCorrect": 4,
			"easeFactor": "2.4",
			"intervalDays": 5,
			"repetitions": 3,
			"nextReview": "2026-03-16T10:00:00Z",
			"lastReview": "2026-03-11T10:00:00Z",
			"createdAt": "2026-01-13T11:00:00Z",
			"updatedAt": "2026-03-11T10:00:00Z"
		},
		{
			"id": "550e8400-e29b-41d4-a716-446655440153",
			"deckId": "550e8400-e29b-41d4-a716-446655440006",
			"front": "Mahatma Gandhi",
			"back": "Indian independence leader, pioneered nonviolent resistance",
			"imageUrl": null,
			"difficulty": "easy",
			"timesReviewed": 7,
			"timesCorrect": 6,
			"easeFactor": "2.6",
			"intervalDays": 8,
			"repetitions": 5,
			"nextReview": "2026-03-18T10:00:00Z",
			"lastReview": "2026-03-10T10:00:00Z",
			"createdAt": "2026-01-13T11:00:00Z",
			"updatedAt": "2026-03-10T10:00:00Z"
		},
		{
			"id": "550e8400-e29b-41d4-a716-446655440154",
			"deckId": "550e8400-e29b-41d4-a716-446655440006",
			"front": "Castro and Cuban Revolution",
			"back": "1959 revolution led by Fidel Castro, established communist state",
			"imageUrl": null,
			"difficulty": "medium",
			"timesReviewed": 4,
			"timesCorrect": 3,
			"easeFactor": "2.3",
			"intervalDays": 4,
			"repetitions": 2,
			"nextReview": "2026-03-15T10:00:00Z",
			"lastReview": "2026-03-11T10:00:00Z",
			"createdAt": "2026-01-13T11:00:00Z",
			"updatedAt": "2026-03-11T10:00:00Z"
		},
		{
			"id": "550e8400-e29b-41d4-a716-446655440155",
			"deckId": "550e8400-e29b-41d4-a716-446655440006",
			"front": "Decolonization of Africa",
			"back": "Wave of African nations gaining independence in 1960s",
			"imageUrl": null,
			"difficulty": "easy",
			"timesReviewed": 7,
			"timesCorrect": 6,
			"easeFactor": "2.6",
			"intervalDays": 8,
			"repetitions": 5,
			"nextReview": "2026-03-18T10:00:00Z",
			"lastReview": "2026-03-10T10:00:00Z",
			"createdAt": "2026-01-14T11:00:00Z",
			"updatedAt": "2026-03-10T10:00:00Z"
		},
		{
			"id": "550e8400-e29b-41d4-a716-446655440156",
			"deckId": "550e8400-e29b-41d4-a716-446655440006",
			"front": "Human Rights",
			"back": "Universal rights inherent to all humans regardless of nationality or status",
			"imageUrl": null,
			"difficulty": "easy",
			"timesReviewed": 7,
			"timesCorrect": 6,
			"easeFactor": "2.6",
			"intervalDays": 8,
			"repetitions": 5,
			"nextReview": "2026-03-18T10:00:00Z",
			"lastReview": "2026-03-10T10:00:00Z",
			"createdAt": "2026-01-14T11:00:00Z",
			"updatedAt": "2026-03-10T10:00:00Z"
		},
		{
			"id": "550e8400-e29b-41d4-a716-446655440157",
			"deckId": "550e8400-e29b-41d4-a716-446655440006",
			"front": "Nationalism",
			"back": "Patriotic feeling or loyalty to one's nation",
			"imageUrl": null,
			"difficulty": "easy",
			"timesReviewed": 6,
			"timesCorrect": 5,
			"easeFactor": "2.5",
			"intervalDays": 7,
			"repetitions": 4,
			"nextReview": "2026-03-17T10:00:00Z",
			"lastReview": "2026-03-10T10:00:00Z",
			"createdAt": "2026-01-15T11:00:00Z",
			"updatedAt": "2026-03-10T10:00:00Z"
		},
		{
			"id": "550e8400-e29b-41d4-a716-446655440158",
			"deckId": "550e8400-e29b-41d4-a716-446655440006",
			"front": "Imperialism",
			"back": "Policy of extending a nation's power through colonization or force",
			"imageUrl": null,
			"difficulty": "easy",
			"timesReviewed": 6,
			"timesCorrect": 5,
			"easeFactor": "2.5",
			"intervalDays": 7,
			"repetitions": 4,
			"nextReview": "2026-03-17T10:00:00Z",
			"lastReview": "2026-03-10T10:00:00Z",
			"createdAt": "2026-01-15T11:00:00Z",
			"updatedAt": "2026-03-10T10:00:00Z"
		},
		{
			"id": "550e8400-e29b-41d4-a716-446655440159",
			"deckId": "550e8400-e29b-41d4-a716-446655440006",
			"front": "Soweto Uprising (June 16, 1976)",
			"back": "Thousands of students marched against forced Afrikaans education, police opened fire",
			"imageUrl": null,
			"difficulty": "medium",
			"timesReviewed": 5,
			"timesCorrect": 4,
			"easeFactor": "2.4",
			"intervalDays": 5,
			"repetitions": 3,
			"nextReview": "2026-03-16T10:00:00Z",
			"lastReview": "2026-03-11T10:00:00Z",
			"createdAt": "2026-01-15T11:00:00Z",
			"updatedAt": "2026-03-11T10:00:00Z"
		},
		{
			"id": "550e8400-e29b-41d4-a716-446655440160",
			"deckId": "550e8400-e29b-41d4-a716-446655440006",
			"front": "Rivonia Trial (1963-1964)",
			"back": "ANC leaders including Mandela sentenced to life imprisonment at Liliesleaf Farm",
			"imageUrl": null,
			"difficulty": "medium",
			"timesReviewed": 4,
			"timesCorrect": 3,
			"easeFactor": "2.3",
			"intervalDays": 4,
			"repetitions": 2,
			"nextReview": "2026-03-15T10:00:00Z",
			"lastReview": "2026-03-11T10:00:00Z",
			"createdAt": "2026-01-16T11:00:00Z",
			"updatedAt": "2026-03-11T10:00:00Z"
		},
		{
			"id": "550e8400-e29b-41d4-a716-446655440161",
			"deckId": "550e8400-e29b-41d4-a716-446655440006",
			"front": "BCM (Black Consciousness Movement)",
			"back": "Movement founded by Steve Biko to restore black South Africans' dignity",
			"imageUrl": null,
			"difficulty": "medium",
			"timesReviewed": 5,
			"timesCorrect": 4,
			"easeFactor": "2.4",
			"intervalDays": 5,
			"repetitions": 3,
			"nextReview": "2026-03-16T10:00:00Z",
			"lastReview": "2026-03-11T10:00:00Z",
			"createdAt": "2026-01-16T11:00:00Z",
			"updatedAt": "2026-03-11T10:00:00Z"
		}
	],
	"flashcardReviewLogs": [
		{
			"id": "660e8400-e29b-41d4-a716-446655440001",
			"userId": "user-1",
			"flashcardId": "card-001",
			"deckId": "550e8400-e29b-41d4-a716-446655440001",
			"rating": "good",
			"responseTimeMs": 3200,
			"reviewedAt": "2026-01-15T10:00:00Z"
		},
		{
			"id": "660e8400-e29b-41d4-a716-446655440002",
			"userId": "user-1",
			"flashcardId": "card-002",
			"deckId": "550e8400-e29b-41d4-a716-446655440001",
			"rating": "easy",
			"responseTimeMs": 2100,
			"reviewedAt": "2026-01-15T10:05:00Z"
		},
		{
			"id": "660e8400-e29b-41d4-a716-446655440003",
			"userId": "user-1",
			"flashcardId": "card-003",
			"deckId": "550e8400-e29b-41d4-a716-446655440001",
			"rating": "good",
			"responseTimeMs": 4500,
			"reviewedAt": "2026-01-16T14:00:00Z"
		},
		{
			"id": "660e8400-e29b-41d4-a716-446655440004",
			"userId": "user-2",
			"flashcardId": "card-027",
			"deckId": "550e8400-e29b-41d4-a716-446655440002",
			"rating": "easy",
			"responseTimeMs": 1800,
			"reviewedAt": "2026-01-15T11:00:00Z"
		},
		{
			"id": "660e8400-e29b-41d4-a716-446655440005",
			"userId": "user-2",
			"flashcardId": "card-028",
			"deckId": "550e8400-e29b-41d4-a716-446655440002",
			"rating": "good",
			"responseTimeMs": 2900,
			"reviewedAt": "2026-01-15T11:10:00Z"
		},
		{
			"id": "660e8400-e29b-41d4-a716-446655440006",
			"userId": "user-1",
			"flashcardId": "card-054",
			"deckId": "550e8400-e29b-41d4-a716-446655440003",
			"rating": "easy",
			"responseTimeMs": 2500,
			"reviewedAt": "2026-01-16T09:00:00Z"
		},
		{
			"id": "660e8400-e29b-41d4-a716-446655440007",
			"userId": "user-1",
			"flashcardId": "card-055",
			"deckId": "550e8400-e29b-41d4-a716-446655440003",
			"rating": "good",
			"responseTimeMs": 3100,
			"reviewedAt": "2026-01-16T09:15:00Z"
		},
		{
			"id": "660e8400-e29b-41d4-a716-446655440008",
			"userId": "user-3",
			"flashcardId": "card-081",
			"deckId": "550e8400-e29b-41d4-a716-446655440004",
			"rating": "easy",
			"responseTimeMs": 2200,
			"reviewedAt": "2026-01-17T10:00:00Z"
		},
		{
			"id": "660e8400-e29b-41d4-a716-446655440009",
			"userId": "user-3",
			"flashcardId": "card-082",
			"deckId": "550e8400-e29b-41d4-a716-446655440004",
			"rating": "easy",
			"responseTimeMs": 2000,
			"reviewedAt": "2026-01-17T10:10:00Z"
		},
		{
			"id": "660e8400-e29b-41d4-a716-446655440010",
			"userId": "user-4",
			"flashcardId": "card-106",
			"deckId": "550e8400-e29b-41d4-a716-446655440005",
			"rating": "good",
			"responseTimeMs": 2800,
			"reviewedAt": "2026-01-18T15:00:00Z"
		},
		{
			"id": "660e8400-e29b-41d4-a716-446655440011",
			"userId": "user-4",
			"flashcardId": "card-107",
			"deckId": "550e8400-e29b-41d4-a716-446655440005",
			"rating": "easy",
			"responseTimeMs": 1900,
			"reviewedAt": "2026-01-18T15:05:00Z"
		},
		{
			"id": "660e8400-e29b-41d4-a716-446655440012",
			"userId": "user-5",
			"flashcardId": "card-127",
			"deckId": "550e8400-e29b-41d4-a716-446655440006",
			"rating": "easy",
			"responseTimeMs": 2400,
			"reviewedAt": "2026-01-19T11:00:00Z"
		},
		{
			"id": "660e8400-e29b-41d4-a716-446655440013",
			"userId": "user-5",
			"flashcardId": "card-128",
			"deckId": "550e8400-e29b-41d4-a716-446655440006",
			"rating": "good",
			"responseTimeMs": 3300,
			"reviewedAt": "2026-01-19T11:10:00Z"
		},
		{
			"id": "660e8400-e29b-41d4-a716-446655440014",
			"userId": "user-1",
			"flashcardId": "card-004",
			"deckId": "550e8400-e29b-41d4-a716-446655440001",
			"rating": "good",
			"responseTimeMs": 3800,
			"reviewedAt": "2026-01-20T10:00:00Z"
		},
		{
			"id": "660e8400-e29b-41d4-a716-446655440015",
			"userId": "user-1",
			"flashcardId": "card-005",
			"deckId": "550e8400-e29b-41d4-a716-446655440001",
			"rating": "hard",
			"responseTimeMs": 5200,
			"reviewedAt": "2026-01-20T10:10:00Z"
		},
		{
			"id": "660e8400-e29b-41d4-a716-446655440016",
			"userId": "user-2",
			"flashcardId": "card-029",
			"deckId": "550e8400-e29b-41d4-a716-446655440002",
			"rating": "easy",
			"responseTimeMs": 1700,
			"reviewedAt": "2026-01-21T09:00:00Z"
		},
		{
			"id": "660e8400-e29b-41d4-a716-446655440017",
			"userId": "user-2",
			"flashcardId": "card-030",
			"deckId": "550e8400-e29b-41d4-a716-446655440002",
			"rating": "easy",
			"responseTimeMs": 2100,
			"reviewedAt": "2026-01-21T09:05:00Z"
		},
		{
			"id": "660e8400-e29b-41d4-a716-446655440018",
			"userId": "user-1",
			"flashcardId": "card-056",
			"deckId": "550e8400-e29b-41d4-a716-446655440003",
			"rating": "easy",
			"responseTimeMs": 1900,
			"reviewedAt": "2026-01-22T08:00:00Z"
		},
		{
			"id": "660e8400-e29b-41d4-a716-446655440019",
			"userId": "user-1",
			"flashcardId": "card-057",
			"deckId": "550e8400-e29b-41d4-a716-446655440003",
			"rating": "good",
			"responseTimeMs": 2900,
			"reviewedAt": "2026-01-22T08:10:00Z"
		},
		{
			"id": "660e8400-e29b-41d4-a716-446655440020",
			"userId": "user-3",
			"flashcardId": "card-083",
			"deckId": "550e8400-e29b-41d4-a716-446655440004",
			"rating": "easy",
			"responseTimeMs": 2300,
			"reviewedAt": "2026-01-23T14:00:00Z"
		},
		{
			"id": "660e8400-e29b-41d4-a716-446655440021",
			"userId": "user-3",
			"flashcardId": "card-084",
			"deckId": "550e8400-e29b-41d4-a716-446655440004",
			"rating": "good",
			"responseTimeMs": 3100,
			"reviewedAt": "2026-01-23T14:10:00Z"
		},
		{
			"id": "660e8400-e29b-41d4-a716-446655440022",
			"userId": "user-4",
			"flashcardId": "card-108",
			"deckId": "550e8400-e29b-41d4-a716-446655440005",
			"rating": "easy",
			"responseTimeMs": 2000,
			"reviewedAt": "2026-01-24T16:00:00Z"
		},
		{
			"id": "660e8400-e29b-41d4-a716-446655440023",
			"userId": "user-4",
			"flashcardId": "card-109",
			"deckId": "550e8400-e29b-41d4-a716-446655440005",
			"rating": "easy",
			"responseTimeMs": 1800,
			"reviewedAt": "2026-01-24T16:05:00Z"
		},
		{
			"id": "660e8400-e29b-41d4-a716-446655440024",
			"userId": "user-5",
			"flashcardId": "card-129",
			"deckId": "550e8400-e29b-41d4-a716-446655440006",
			"rating": "good",
			"responseTimeMs": 3400,
			"reviewedAt": "2026-01-25T10:00:00Z"
		},
		{
			"id": "log-025",
			"userId": "user-5",
			"flashcardId": "card-130",
			"deckId": "550e8400-e29b-41d4-a716-446655440006",
			"rating": "easy",
			"responseTimeMs": 2200,
			"reviewedAt": "2026-01-25T10:10:00Z"
		},
		{
			"id": "log-026",
			"userId": "Themba",
			"flashcardId": "card-001",
			"deckId": "550e8400-e29b-41d4-a716-446655440001",
			"rating": "good",
			"responseTimeMs": 2800,
			"reviewedAt": "2026-02-01T09:00:00Z"
		},
		{
			"id": "log-027",
			"userId": "Themba",
			"flashcardId": "card-006",
			"deckId": "550e8400-e29b-41d4-a716-446655440001",
			"rating": "easy",
			"responseTimeMs": 1500,
			"reviewedAt": "2026-02-01T09:10:00Z"
		},
		{
			"id": "log-028",
			"userId": "Amahle",
			"flashcardId": "card-027",
			"deckId": "550e8400-e29b-41d4-a716-446655440002",
			"rating": "easy",
			"responseTimeMs": 1700,
			"reviewedAt": "2026-02-02T10:00:00Z"
		},
		{
			"id": "log-029",
			"userId": "Amahle",
			"flashcardId": "card-033",
			"deckId": "550e8400-e29b-41d4-a716-446655440002",
			"rating": "good",
			"responseTimeMs": 2600,
			"reviewedAt": "2026-02-02T10:10:00Z"
		},
		{
			"id": "log-030",
			"userId": "Sipho",
			"flashcardId": "card-054",
			"deckId": "550e8400-e29b-41d4-a716-446655440003",
			"rating": "easy",
			"responseTimeMs": 1900,
			"reviewedAt": "2026-02-03T11:00:00Z"
		},
		{
			"id": "log-031",
			"userId": "Sipho",
			"flashcardId": "card-062",
			"deckId": "550e8400-e29b-41d4-a716-446655440003",
			"rating": "good",
			"responseTimeMs": 2700,
			"reviewedAt": "2026-02-03T11:10:00Z"
		},
		{
			"id": "log-032",
			"userId": "Lwazi",
			"flashcardId": "card-081",
			"deckId": "550e8400-e29b-41d4-a716-446655440004",
			"rating": "easy",
			"responseTimeMs": 2100,
			"reviewedAt": "2026-02-04T08:00:00Z"
		},
		{
			"id": "log-033",
			"userId": "Lwazi",
			"flashcardId": "card-094",
			"deckId": "550e8400-e29b-41d4-a716-446655440004",
			"rating": "good",
			"responseTimeMs": 3000,
			"reviewedAt": "2026-02-04T08:10:00Z"
		},
		{
			"id": "log-034",
			"userId": "Naledi",
			"flashcardId": "card-106",
			"deckId": "550e8400-e29b-41d4-a716-446655440005",
			"rating": "easy",
			"responseTimeMs": 1800,
			"reviewedAt": "2026-02-05T15:00:00Z"
		},
		{
			"id": "log-035",
			"userId": "Naledi",
			"flashcardId": "card-113",
			"deckId": "550e8400-e29b-41d4-a716-446655440005",
			"rating": "good",
			"responseTimeMs": 2500,
			"reviewedAt": "2026-02-05T15:10:00Z"
		},
		{
			"id": "log-036",
			"userId": "Themba",
			"flashcardId": "card-127",
			"deckId": "550e8400-e29b-41d4-a716-446655440006",
			"rating": "easy",
			"responseTimeMs": 2300,
			"reviewedAt": "2026-02-06T10:00:00Z"
		},
		{
			"id": "log-037",
			"userId": "Themba",
			"flashcardId": "card-133",
			"deckId": "550e8400-e29b-41d4-a716-446655440006",
			"rating": "easy",
			"responseTimeMs": 2000,
			"reviewedAt": "2026-02-06T10:10:00Z"
		},
		{
			"id": "log-038",
			"userId": "Amahle",
			"flashcardId": "card-007",
			"deckId": "550e8400-e29b-41d4-a716-446655440001",
			"rating": "easy",
			"responseTimeMs": 1600,
			"reviewedAt": "2026-02-10T09:00:00Z"
		},
		{
			"id": "log-039",
			"userId": "Amahle",
			"flashcardId": "card-014",
			"deckId": "550e8400-e29b-41d4-a716-446655440001",
			"rating": "easy",
			"responseTimeMs": 1400,
			"reviewedAt": "2026-02-10T09:10:00Z"
		},
		{
			"id": "log-040",
			"userId": "Sipho",
			"flashcardId": "card-037",
			"deckId": "550e8400-e29b-41d4-a716-446655440002",
			"rating": "good",
			"responseTimeMs": 3200,
			"reviewedAt": "2026-02-11T14:00:00Z"
		},
		{
			"id": "log-041",
			"userId": "Sipho",
			"flashcardId": "card-039",
			"deckId": "550e8400-e29b-41d4-a716-446655440002",
			"rating": "easy",
			"responseTimeMs": 1900,
			"reviewedAt": "2026-02-11T14:10:00Z"
		},
		{
			"id": "log-042",
			"userId": "Lwazi",
			"flashcardId": "card-065",
			"deckId": "550e8400-e29b-41d4-a716-446655440003",
			"rating": "easy",
			"responseTimeMs": 1700,
			"reviewedAt": "2026-02-12T08:00:00Z"
		},
		{
			"id": "log-043",
			"userId": "Lwazi",
			"flashcardId": "card-069",
			"deckId": "550e8400-e29b-41d4-a716-446655440003",
			"rating": "good",
			"responseTimeMs": 2800,
			"reviewedAt": "2026-02-12T08:10:00Z"
		},
		{
			"id": "log-044",
			"userId": "Naledi",
			"flashcardId": "card-085",
			"deckId": "550e8400-e29b-41d4-a716-446655440004",
			"rating": "easy",
			"responseTimeMs": 2100,
			"reviewedAt": "2026-02-13T10:00:00Z"
		},
		{
			"id": "log-045",
			"userId": "Naledi",
			"flashcardId": "card-089",
			"deckId": "550e8400-e29b-41d4-a716-446655440004",
			"rating": "hard",
			"responseTimeMs": 4500,
			"reviewedAt": "2026-02-13T10:10:00Z"
		},
		{
			"id": "log-046",
			"userId": "Themba",
			"flashcardId": "card-117",
			"deckId": "550e8400-e29b-41d4-a716-446655440005",
			"rating": "easy",
			"responseTimeMs": 1500,
			"reviewedAt": "2026-02-14T16:00:00Z"
		},
		{
			"id": "log-047",
			"userId": "Themba",
			"flashcardId": "card-118",
			"deckId": "550e8400-e29b-41d4-a716-446655440005",
			"rating": "easy",
			"responseTimeMs": 1600,
			"reviewedAt": "2026-02-14T16:05:00Z"
		},
		{
			"id": "log-048",
			"userId": "Amahle",
			"flashcardId": "card-141",
			"deckId": "550e8400-e29b-41d4-a716-446655440006",
			"rating": "good",
			"responseTimeMs": 3000,
			"reviewedAt": "2026-02-15T11:00:00Z"
		},
		{
			"id": "log-049",
			"userId": "Amahle",
			"flashcardId": "card-145",
			"deckId": "550e8400-e29b-41d4-a716-446655440006",
			"rating": "easy",
			"responseTimeMs": 2200,
			"reviewedAt": "2026-02-15T11:10:00Z"
		},
		{
			"id": "log-050",
			"userId": "Sipho",
			"flashcardId": "card-015",
			"deckId": "550e8400-e29b-41d4-a716-446655440001",
			"rating": "hard",
			"responseTimeMs": 5800,
			"reviewedAt": "2026-02-20T10:00:00Z"
		},
		{
			"id": "log-051",
			"userId": "Sipho",
			"flashcardId": "card-017",
			"deckId": "550e8400-e29b-41d4-a716-446655440001",
			"rating": "again",
			"responseTimeMs": 6200,
			"reviewedAt": "2026-02-20T10:15:00Z"
		},
		{
			"id": "log-052",
			"userId": "Lwazi",
			"flashcardId": "card-048",
			"deckId": "550e8400-e29b-41d4-a716-446655440002",
			"rating": "hard",
			"responseTimeMs": 5400,
			"reviewedAt": "2026-02-21T09:00:00Z"
		},
		{
			"id": "log-053",
			"userId": "Lwazi",
			"flashcardId": "card-044",
			"deckId": "550e8400-e29b-41d4-a716-446655440002",
			"rating": "again",
			"responseTimeMs": 6100,
			"reviewedAt": "2026-02-21T09:15:00Z"
		},
		{
			"id": "log-054",
			"userId": "Naledi",
			"flashcardId": "card-024",
			"deckId": "550e8400-e29b-41d4-a716-446655440001",
			"rating": "hard",
			"responseTimeMs": 4900,
			"reviewedAt": "2026-02-22T14:00:00Z"
		},
		{
			"id": "log-055",
			"userId": "Naledi",
			"flashcardId": "card-025",
			"deckId": "550e8400-e29b-41d4-a716-446655440001",
			"rating": "hard",
			"responseTimeMs": 5200,
			"reviewedAt": "2026-02-22T14:10:00Z"
		},
		{
			"id": "log-056",
			"userId": "Themba",
			"flashcardId": "card-078",
			"deckId": "550e8400-e29b-41d4-a716-446655440003",
			"rating": "good",
			"responseTimeMs": 3100,
			"reviewedAt": "2026-02-25T08:00:00Z"
		},
		{
			"id": "log-057",
			"userId": "Themba",
			"flashcardId": "card-091",
			"deckId": "550e8400-e29b-41d4-a716-446655440004",
			"rating": "good",
			"responseTimeMs": 3400,
			"reviewedAt": "2026-02-25T08:10:00Z"
		},
		{
			"id": "log-058",
			"userId": "Amahle",
			"flashcardId": "card-112",
			"deckId": "550e8400-e29b-41d4-a716-446655440005",
			"rating": "good",
			"responseTimeMs": 2900,
			"reviewedAt": "2026-02-26T15:00:00Z"
		},
		{
			"id": "log-059",
			"userId": "Amahle",
			"flashcardId": "card-120",
			"deckId": "550e8400-e29b-41d4-a716-446655440005",
			"rating": "good",
			"responseTimeMs": 3200,
			"reviewedAt": "2026-02-26T15:10:00Z"
		},
		{
			"id": "log-060",
			"userId": "Sipho",
			"flashcardId": "card-137",
			"deckId": "550e8400-e29b-41d4-a716-446655440006",
			"rating": "good",
			"responseTimeMs": 3000,
			"reviewedAt": "2026-02-27T11:00:00Z"
		},
		{
			"id": "log-061",
			"userId": "Sipho",
			"flashcardId": "card-139",
			"deckId": "550e8400-e29b-41d4-a716-446655440006",
			"rating": "good",
			"responseTimeMs": 2800,
			"reviewedAt": "2026-02-27T11:10:00Z"
		},
		{
			"id": "log-062",
			"userId": "user-1",
			"flashcardId": "card-008",
			"deckId": "550e8400-e29b-41d4-a716-446655440001",
			"rating": "good",
			"responseTimeMs": 2900,
			"reviewedAt": "2026-03-01T10:00:00Z"
		},
		{
			"id": "log-063",
			"userId": "user-1",
			"flashcardId": "card-009",
			"deckId": "550e8400-e29b-41d4-a716-446655440001",
			"rating": "hard",
			"responseTimeMs": 4600,
			"reviewedAt": "2026-03-01T10:10:00Z"
		},
		{
			"id": "log-064",
			"userId": "user-2",
			"flashcardId": "card-031",
			"deckId": "550e8400-e29b-41d4-a716-446655440002",
			"rating": "good",
			"responseTimeMs": 3100,
			"reviewedAt": "2026-03-02T09:00:00Z"
		},
		{
			"id": "log-065",
			"userId": "user-2",
			"flashcardId": "card-032",
			"deckId": "550e8400-e29b-41d4-a716-446655440002",
			"rating": "good",
			"responseTimeMs": 3300,
			"reviewedAt": "2026-03-02T09:10:00Z"
		}
	]
}
